Workbook

Sheet Placar
A1: Placar da checagem — Debate Globo, 2º turno 2026 (23/10/2026)
A2: Flávio Bolsonaro (PL) × Lula (PT) · cada declaração pesquisada por um agente e conferida por outro agente independente
A4: Veredito | B4: Flávio Bolsonaro | C4: Lula | D4: Total
A5: Verdadeiro | B5: =COUNTIFS(Checagens!$B$2:$B$92,"Flávio",Checagens!$E$2:$E$92,A5) | C5: =COUNTIFS(Checagens!$B$2:$B$92,"Lula",Checagens!$E$2:$E$92,A5) | D5: =B5+C5
A6: Verdadeiro, mas impreciso | B6: =COUNTIFS(Checagens!$B$2:$B$92,"Flávio",Checagens!$E$2:$E$92,A6) | C6: =COUNTIFS(Checagens!$B$2:$B$92,"Lula",Checagens!$E$2:$E$92,A6) | D6: =B6+C6
A7: Exagerado | B7: =COUNTIFS(Checagens!$B$2:$B$92,"Flávio",Checagens!$E$2:$E$92,A7) | C7: =COUNTIFS(Checagens!$B$2:$B$92,"Lula",Checagens!$E$2:$E$92,A7) | D7: =B7+C7
A8: Falso | B8: =COUNTIFS(Checagens!$B$2:$B$92,"Flávio",Checagens!$E$2:$E$92,A8) | C8: =COUNTIFS(Checagens!$B$2:$B$92,"Lula",Checagens!$E$2:$E$92,A8) | D8: =B8+C8
A9: Sem evidência | B9: =COUNTIFS(Checagens!$B$2:$B$92,"Flávio",Checagens!$E$2:$E$92,A9) | C9: =COUNTIFS(Checagens!$B$2:$B$92,"Lula",Checagens!$E$2:$E$92,A9) | D9: =B9+C9
A10: Total de declarações checadas | B10: =SUM(B5:B9) | C10: =SUM(C5:C9) | D10: =B10+C10
A12: RESUMO
A13: Verdades (Verdadeiro + Verdadeiro, mas impreciso) | B13: =B5+B6 | C13: =C5+C6 | D13: =B13+C13
A14: Falsas (Falso) | B14: =B8 | C14: =C8 | D14: =B14+C14
A15: Exageradas | B15: =B7 | C15: =C7 | D15: =B15+C15
A16: Sem evidência | B16: =B9 | C16: =C9 | D16: =B16+C16
A17: % de verdades | B17: =IF(B10=0,0,B13/B10) | C17: =IF(C10=0,0,C13/C10) | D17: =IF(D10=0,0,D13/D10)
A18: % de falsas + exageradas | B18: =IF(B10=0,0,(B14+B15)/B10) | C18: =IF(C10=0,0,(C14+C15)/C10) | D18: =IF(D10=0,0,(D14+D15)/D10)
A20: Revisões em que o agente revisor discordou da pesquisa inicial | B20: =COUNTIF(Checagens!$I$2:$I$92,"Não")
A22: Critérios: "verdades" = Verdadeiro + Verdadeiro, mas impreciso; "falsas" = Falso. Exagerado e Sem evidência aparecem à parte. Detalhes na aba Metodologia.

Sheet Placar Promessas
A1: Viabilidade das promessas, mandato 2027-2030
A2: Viabilidade (%) = chance estimada de a promessa ser cumprida em boa parte até 2030, considerando custo/espaço fiscal, exigências legais, competência federativa, prazo e realidade regional.
A4: Indicador | B4: Flávio Bolsonaro | C4: Lula | D4: Total
A5: Promessas analisadas | B5: =COUNTIF(Promessas!$B$2:$B$41,"Flávio") | C5: =COUNTIF(Promessas!$B$2:$B$41,"Lula") | D5: =B5+C5
A6: Viabilidade média | B6: =IFERROR(AVERAGEIF(Promessas!$B$2:$B$41,"Flávio",Promessas!$F$2:$F$41),0) | C6: =IFERROR(AVERAGEIF(Promessas!$B$2:$B$41,"Lula",Promessas!$F$2:$F$41),0) | D6: =AVERAGE(Promessas!$F$2:$F$41)
A7: Viabilidade mais alta | B7: =SUMPRODUCT(MAX((Promessas!$B$2:$B$41="Flávio")*Promessas!$F$2:$F$41)) | C7: =SUMPRODUCT(MAX((Promessas!$B$2:$B$41="Lula")*Promessas!$F$2:$F$41)) | D7: =MAX(Promessas!$F$2:$F$41)
A8: Viabilidade mais baixa | B8: =SUMPRODUCT(MIN((Promessas!$B$2:$B$41="Flávio")*Promessas!$F$2:$F$41+(Promessas!$B$2:$B$41<>"Flávio")*2)) | C8: =SUMPRODUCT(MIN((Promessas!$B$2:$B$41="Lula")*Promessas!$F$2:$F$41+(Promessas!$B$2:$B$41<>"Lula")*2)) | D8: =MIN(Promessas!$F$2:$F$41)
A9: Alta viabilidade (70-100%) | B9: =COUNTIFS(Promessas!$B$2:$B$41,"Flávio",Promessas!$G$2:$G$41,"Alta") | C9: =COUNTIFS(Promessas!$B$2:$B$41,"Lula",Promessas!$G$2:$G$41,"Alta") | D9: =B9+C9
A10: Média viabilidade (40-69%) | B10: =COUNTIFS(Promessas!$B$2:$B$41,"Flávio",Promessas!$G$2:$G$41,"Média") | C10: =COUNTIFS(Promessas!$B$2:$B$41,"Lula",Promessas!$G$2:$G$41,"Média") | D10: =B10+C10
A11: Baixa viabilidade (0-39%) | B11: =COUNTIFS(Promessas!$B$2:$B$41,"Flávio",Promessas!$G$2:$G$41,"Baixa") | C11: =COUNTIFS(Promessas!$B$2:$B$41,"Lula",Promessas!$G$2:$G$41,"Baixa") | D11: =B11+C11
A12: % de promessas com alta viabilidade | B12: =IF(B5=0,0,B9/B5) | C12: =IF(C5=0,0,C9/C5) | D12: =IF(D5=0,0,D9/D5)
A15: Viabilidade média por tema
A16: Tema (grupo) | B16: Flávio Bolsonaro | C16: Lula | D16: Nº promessas
A17: Agro | B17: =IFERROR(AVERAGEIFS(Promessas!$F$2:$F$41,Promessas!$B$2:$B$41,"Flávio",Promessas!$R$2:$R$41,A17),"—") | C17: =IFERROR(AVERAGEIFS(Promessas!$F$2:$F$41,Promessas!$B$2:$B$41,"Lula",Promessas!$R$2:$R$41,A17),"—") | D17: =COUNTIF(Promessas!$R$2:$R$41,A17)
A18: Apostas | B18: =IFERROR(AVERAGEIFS(Promessas!$F$2:$F$41,Promessas!$B$2:$B$41,"Flávio",Promessas!$R$2:$R$41,A18),"—") | C18: =IFERROR(AVERAGEIFS(Promessas!$F$2:$F$41,Promessas!$B$2:$B$41,"Lula",Promessas!$R$2:$R$41,A18),"—") | D18: =COUNTIF(Promessas!$R$2:$R$41,A18)
A19: Economia | B19: =IFERROR(AVERAGEIFS(Promessas!$F$2:$F$41,Promessas!$B$2:$B$41,"Flávio",Promessas!$R$2:$R$41,A19),"—") | C19: =IFERROR(AVERAGEIFS(Promessas!$F$2:$F$41,Promessas!$B$2:$B$41,"Lula",Promessas!$R$2:$R$41,A19),"—") | D19: =COUNTIF(Promessas!$R$2:$R$41,A19)
A20: Educação | B20: =IFERROR(AVERAGEIFS(Promessas!$F$2:$F$41,Promessas!$B$2:$B$41,"Flávio",Promessas!$R$2:$R$41,A20),"—") | C20: =IFERROR(AVERAGEIFS(Promessas!$F$2:$F$41,Promessas!$B$2:$B$41,"Lula",Promessas!$R$2:$R$41,A20),"—") | D20: =COUNTIF(Promessas!$R$2:$R$41,A20)
A21: Indígenas | B21: =IFERROR(AVERAGEIFS(Promessas!$F$2:$F$41,Promessas!$B$2:$B$41,"Flávio",Promessas!$R$2:$R$41,A21),"—") | C21: =IFERROR(AVERAGEIFS(Promessas!$F$2:$F$41,Promessas!$B$2:$B$41,"Lula",Promessas!$R$2:$R$41,A21),"—") | D21: =COUNTIF(Promessas!$R$2:$R$41,A21)
A22: Infraestrutura | B22: =IFERROR(AVERAGEIFS(Promessas!$F$2:$F$41,Promessas!$B$2:$B$41,"Flávio",Promessas!$R$2:$R$41,A22),"—") | C22: =IFERROR(AVERAGEIFS(Promessas!$F$2:$F$41,Promessas!$B$2:$B$41,"Lula",Promessas!$R$2:$R$41,A22),"—") | D22: =COUNTIF(Promessas!$R$2:$R$41,A22)
A23: Mobilidade | B23: =IFERROR(AVERAGEIFS(Promessas!$F$2:$F$41,Promessas!$B$2:$B$41,"Flávio",Promessas!$R$2:$R$41,A23),"—") | C23: =IFERROR(AVERAGEIFS(Promessas!$F$2:$F$41,Promessas!$B$2:$B$41,"Lula",Promessas!$R$2:$R$41,A23),"—") | D23: =COUNTIF(Promessas!$R$2:$R$41,A23)
A24: Mulheres | B24: =IFERROR(AVERAGEIFS(Promessas!$F$2:$F$41,Promessas!$B$2:$B$41,"Flávio",Promessas!$R$2:$R$41,A24),"—") | C24: =IFERROR(AVERAGEIFS(Promessas!$F$2:$F$41,Promessas!$B$2:$B$41,"Lula",Promessas!$R$2:$R$41,A24),"—") | D24: =COUNTIF(Promessas!$R$2:$R$41,A24)
A25: Nordeste | B25: =IFERROR(AVERAGEIFS(Promessas!$F$2:$F$41,Promessas!$B$2:$B$41,"Flávio",Promessas!$R$2:$R$41,A25),"—") | C25: =IFERROR(AVERAGEIFS(Promessas!$F$2:$F$41,Promessas!$B$2:$B$41,"Lula",Promessas!$R$2:$R$41,A25),"—") | D25: =COUNTIF(Promessas!$R$2:$R$41,A25)
A26: Norte | B26: =IFERROR(AVERAGEIFS(Promessas!$F$2:$F$41,Promessas!$B$2:$B$41,"Flávio",Promessas!$R$2:$R$41,A26),"—") | C26: =IFERROR(AVERAGEIFS(Promessas!$F$2:$F$41,Promessas!$B$2:$B$41,"Lula",Promessas!$R$2:$R$41,A26),"—") | D26: =COUNTIF(Promessas!$R$2:$R$41,A26)
A27: Saúde | B27: =IFERROR(AVERAGEIFS(Promessas!$F$2:$F$41,Promessas!$B$2:$B$41,"Flávio",Promessas!$R$2:$R$41,A27),"—") | C27: =IFERROR(AVERAGEIFS(Promessas!$F$2:$F$41,Promessas!$B$2:$B$41,"Lula",Promessas!$R$2:$R$41,A27),"—") | D27: =COUNTIF(Promessas!$R$2:$R$41,A27)
A28: Segurança | B28: =IFERROR(AVERAGEIFS(Promessas!$F$2:$F$41,Promessas!$B$2:$B$41,"Flávio",Promessas!$R$2:$R$41,A28),"—") | C28: =IFERROR(AVERAGEIFS(Promessas!$F$2:$F$41,Promessas!$B$2:$B$41,"Lula",Promessas!$R$2:$R$41,A28),"—") | D28: =COUNTIF(Promessas!$R$2:$R$41,A28)
... A31: Trabalho | B31: =IFERROR(AVERAGEIFS(Promessas!$F$2:$F$41,Promessas!$B$2:$B$41,"Flávio",Promessas!$R$2:$R$41,A31),"—") | C31: =IFERROR(AVERAGEIFS(Promessas!$F$2:$F$41,Promessas!$B$2:$B$41,"Lula",Promessas!$R$2:$R$41,A31),"—") | D31: =COUNTIF(Promessas!$R$2:$R$41,A31)
A33: "—" = o candidato não fez promessa nesse tema. A média geral pesa igualmente cada promessa; o detalhe está na aba Promessas.

Sheet Checagens
A1: ID | B1: Candidato | C1: Tempo no vídeo | D1: Declaração (resumo) | E1: Veredito final | F1: Explicação (resumo) | G1: Confiança | H1: Veredito da pesquisa inicial | I1: Revisor concordou? | J1: Nota do revisor independente | K1: Principais fontes
A2: F01 | B2: Flávio | C2: 00:07 | D2: O governo Bolsonaro recebeu o país em 2019 com cerca de 14.000 obras inacabadas e entregou com pouco mais de 8.000. | E2: Verdadeiro, mas impreciso | F2: Os números se aproximam dos levantamentos do TCU. A auditoria do Acórdão 1.079/2019, feita entre 2017 e 2019, achou cerca de 14 mil obras paralisadas num total de 38 mil (cerca de 37%). O levantamento julgado pelo TCU em 18/10/2023, que O Povo associa à situação de 2022, achou 8.603 obras paralisadas, mas num universo bem menor, de 21.007. A queda absoluta existe. A proporção de obras paradas, porém, subiu de cerca de 29% em 2020 (7.862 de 27.126) para 41%. O TCU também concluiu que não existiu, entre 2019 e 2022, política pública para resolver o problema das obras paralisadas. | G2: Alta | H2: Verdadeiro, mas impreciso | I2: Sim | J2: REAVALIADO SEM FONTES ENVIESADAS. Veredito mantido. Saíram o 8.674 e o 14,4 mil em 38,4 mil, que só vinham da Gazeta do Povo. Entraram os números oficiais do TCU: 8.603 em 21.007 e cerca de 14 mil em 38 mil. O Jornal Opção não foi usado. Revisor: Abri todas as fontes citadas, e elas são permitidas e confirmam o que o agente afirma. O 8.603/21.007 e os 29% e 41% estão na notícia do TCU. O 14 mil em 38 mil está no relatório do TCU de 2019. A frase sobre a falta de política pública entre 2019 e 2022 está em O Povo. Um ajuste: a notícia do TCU dá como data dos dados a sessão de 18/10/2023, e a ligação com 2022 vem de O Povo. O texto foi ajustado para refletir isso. Nenhum dado depende de fonte excluída. | K2: https://portal.tcu.gov.br/imprensa/noticias/brasil-tem-86-mil-obras-paralisadas-financiadas-com-recursos-federais https://sites.tcu.gov.br/relatorio-de-politicas/2019/area_12.htm https://www.opovo.com.br/noticias/economia/2023/10/18/tcu-diz-que-nao-existiu-entre-2019-e-2022-politicas-para-obras-paralisadas-e-cobra-medidas.html
A3: F02 | B3: Flávio | C3: 00:07 | D3: O TCU acaba de soltar (2026) relatório apontando mais de 11.500 obras paralisadas no atual governo. | E3: Verdadeiro, mas impreciso | F3: Em 30/07/2025, o TCU divulgou que 11.469 das 22.621 obras com recursos federais (50,7%) estavam paralisadas em abril de 2025. O número fica um pouco abaixo dos 'mais de 11.500' citados, e o relatório é de 2025, não de 2026. O estoque também reúne obras iniciadas em gestões anteriores: das 5.505 obras iniciadas entre abril de 2024 e abril de 2025, cerca de 1,2 mil (22%) estavam paradas. | G3: Alta | H3: Verdadeiro, mas impreciso | I3: Sim | J3: REAVALIADO SEM FONTES ENVIESADAS. Nada mudou na substância. Revisor: Confirmei no TCU e no Viva os números 11.469 de 22.621 (50,7%), a data de 30/07/2025, a referência a abril de 2025 e as cerca de 1,2 mil paradas entre as 5.505 obras recentes. Acrescentei à explicação que 11.469 fica levemente abaixo de 'mais de 11.500'. Nenhum dado depende de fonte excluída. | K3: https://portal.tcu.gov.br/imprensa/noticias/metade-das-obras-financiadas-com-recursos-federais-estao-paradas https://viva.com.br/noticias/brasil-tem-mais-de-11-mil-obras-paradas-para-tcu-volume-e-preocupante.html
A4: F03 | B4: Flávio | C4: 00:10 | D4: Regra do governo Bolsonaro garante pedágio zero para motociclistas em todas as novas concessões federais de rodovias. | E4: Exagerado | F4: A Portaria 104/2021 do Ministério da Infraestrutura fixou como diretriz a isenção de pedágio para motos nos editais de 11 rodovias federais então em licitação, como Dutra, Fernão Dias e BR-040. Não é uma regra que garanta a isenção em todas as novas concessões federais: cada contrato define a questão separadamente. A ideia de valer para todas foi uma promessa de Bolsonaro. | G4: Média | H4: Verdadeiro, mas impreciso | I4: Não | J4: A base da pesquisa original está correta, mas o InfoMoney confirma que a portaria se limitava a 11 rodovias específicas e que cada contrato é negociado separadamente. Por isso a palavra 'garante' com 'todas as novas concessões' infla a medida, e mudei o veredito de 'Verdadeiro, mas impreciso' para 'Exagerado'. Descartei as fontes de blogs de motos. | K4: https://www.infomoney.com.br/?p=1881372 https://oespecialista.safra.com.br/tcu-aprova-concessao-da-dutra-e-isencao-de-pedagio-para-motos/ https://www.motoo.com.br/novas-concessoes-de-rodovias-federais-terao-isencao-de-pedagio-para-motos/ https://www.agazeta.com.br/es/economia/motos-ficarao-livres-de-pagar-pedagio-na-br-262-apos-concessao-0721
A5: F04 | B5: Flávio | C5: 00:10 | D5: O governo Bolsonaro instalou mais de 21.300 pontos de internet, em mais de 3.100 cidades, atendendo mais de 11 milhões de brasileiros (escolas, unidades de saúde, aldeias). | E5: Verdadeiro, mas impreciso | F5: Os números batem com o balanço oficial do Ministério das Comunicações. O texto foi publicado no portal gov.br em 19/12/2022 e republicado pelo NIC.br em 20/12/2022; abri a página. Segundo ele, o Wi-Fi Brasil tinha 21,3 mil pontos de internet gratuita, atendia mais de 11 milhões de brasileiros em cerca de 3,2 mil cidades, e 16.195 conexões (76,2%) ficavam em escolas. Os 21.300 pontos, as mais de 3.100 cidades e os mais de 11 milhões de pessoas citados por Flávio estão, portanto, corretos. A imprecisão está em dizer que o governo Bolsonaro 'instalou' todos esses pontos. O Wi-Fi Brasil é a continuação do antigo programa GESAC, criado em 2002, e parte das conexões já existia antes de 2019. Em abril de 2021 a Agência Brasil já falava em mais de 13 mil pontos. A grande expansão aconteceu em 2021-2022, mas o total acumulado não foi instalado só nessa gestão. O balanço que abri não traz números separados de unidades de saúde e aldeias, apenas a menção genérica. | G5: Alta | H5: Verdadeiro, mas impreciso | I5: Sim | J5: RECHECADO (2ª rodada). Concordo com o veredito e agora há confirmação do número exato, que o agente anterior não havia achado: o balanço oficial de dezembro de 2022 confirma 21,3 mil pontos, cerca de 3,2 mil cidades e mais de 11 milhões de pessoas. A ressalva sobre a origem no GESAC (2002) continua válida. Observação: o limite de buscas da sessão se esgotou depois da primeira consulta, então a revisão se apoiou em páginas abertas com WebFetch. | K5: https://www.nic.br/noticia/na-midia/mais-de-21-3-mil-pontos-de-internet-do-wi-fi-brasil-sao-instalados/ https://agenciabrasil.ebc.com.br/geral/noticia/2021-04/programa-leva-internet-areas-remotas-do-pais https://www.minhaoperadora.com.br/2022/06/governo-entregou-mais-de-17-mil-pontos-wi-fi-a-populacao.html https://agenciasebrae.com.br/inovacao/wi-fi-brasil-sebrae-inicia-instalacao-dos-pontos-de-conexao
A6: F05 | B6: Flávio | C6: 00:18 | D6: Lula implementou a carga tributária mais alta da história do país. | E6: Verdadeiro, mas impreciso | F6: Pelos dados preliminares do Tesouro Nacional (abril de 2026), a carga tributária bruta de 2025 foi de 32,4% do PIB, a maior da série iniciada em 2010. Chamar isso de 'mais alta da história' vale só para essa série. A alta sobre 2024 foi pequena e se deve em parte ao comportamento da arrecadação, não apenas a novos tributos criados pelo governo. | G6: Média | H6: Verdadeiro, mas impreciso | I6: Sim | J6: Confirmei os 32,4% e que a série do Tesouro começa em 2010. A ressalva sobre séries anteriores, com outra metodologia, segue válida. As fontes usadas são portais secundários que reproduzem o Tesouro. Não acessei a nota oficial do Tesouro porque o limite de buscas acabou. | K6: https://www.reformatributaria.com/economia-reforma-tributaria-impactos/carga-tributaria-bate-recorde-em-2025-e-atinge-324-do-pib/ https://economicnewsbrasil.com.br/2026/04/11/carga-tributaria-brasil-2025-tesouro-dados/ https://www.contabeis.com.br/noticias/76330/carga-tributaria-do-brasil-atinge-recorde-de-32-4-do-pib-em-2025/
A7: F06 | B7: Flávio | C7: 00:18 | D7: A alíquota do novo IVA da reforma tributária é estimada em cerca de 28% e será o maior IVA do mundo; o governo já deveria ter enviado ao Congresso projeto definindo a alíquota. | E7: Verdadeiro, mas impreciso | F7: As estimativas do IVA dual ficaram em cerca de 28%: 27,97% no texto da Câmara e 28,55% após o Senado, segundo o relator Eduardo Braga. Isso supera os 27% da Hungria. Mas não há atraso no envio de projeto: pela lei complementar, se a alíquota de referência passar de 26,5%, o governo tem 90 dias a partir de dezembro de 2030 para enviar um projeto que reduza incentivos fiscais. | G7: Média | H7: Verdadeiro, mas impreciso | I7: Sim | J7: Confirmei no InfoMoney os 28,55%, a comparação com a Hungria e o prazo de 2030/2031. A segunda parte da fala é falsa. Mantive 'Verdadeiro, mas impreciso' porque o núcleo da afirmação, a alíquota de cerca de 28% e o maior IVA do mundo, se sustenta. Seria defensável também chamar a fala inteira de 'Exagerada'. | K7: https://www.infomoney.com.br/?p=2703795 https://www.moneytimes.com.br/brasil-tera-maior-aliquota-do-mundo-apos-reforma-tributaria-no-senado-jals/ https://edicao.correiobraziliense.com.br/correiobraziliense/2025/01/17/13530f/pdf/A02-POL-1701-DIG.pdf
A8: F07 | B8: Flávio | C8: 00:19 | D8: Foi Bolsonaro que estabeleceu o benefício mínimo de R$ 600 do Bolsa Família/Auxílio Brasil. | E8: Exagerado | F8: O governo Bolsonaro pagou o Auxílio Brasil de R$ 600 em 2022. O valor veio de um acréscimo temporário de R$ 200, aprovado pela chamada PEC das Bondades (ou PEC Kamikaze), que valia só até dezembro de 2022. Sem nova medida, o benefício voltaria a R$ 400 em janeiro de 2023. A manutenção dos R$ 600 em 2023 veio da PEC articulada pela equipe de transição de Lula, que ampliou o teto de gastos. O piso de R$ 600 por família, garantido por complementação, foi fixado pela Lei 14.601/2023, que recriou o Bolsa Família. Bolsonaro de fato pagou R$ 600, mas de forma temporária, e não estabeleceu o piso permanente. | G8: Alta | H8: Exagerado | I8: Sim | J8: REAVALIADO SEM FONTES ENVIESADAS. Veredito mantido. Saiu a Crusoé. A previsão do Orçamento de 2023 deu lugar ao dado confirmado de que o valor voltaria a R$ 400 em janeiro de 2023. Entrou a Lei 14.601/2023 como base do piso permanente. A referência ao número da EC 126 saiu. Revisor: O Correio Braziliense confirma a PEC das Bondades/Kamikaze e o acréscimo de R$ 200 válido até dezembro. O Jornal Contábil confirma a volta a R$ 400 sem nova medida e a PEC da equipe de Lula que ampliou o teto. A Câmara confirma o piso de R$ 600 por complementação na Lei 14.601/2023. A página do Planalto não abriu (timeout) e foi retirada das fontes, o que não muda o resultado porque a Câmara já confirma a lei. Tirei também o 'a partir de agosto', que nenhuma das fontes abertas confirma de forma explícita. Nenhum dado depende de fonte excluída. | K8: https://www.correiobraziliense.com.br/politica/2022/08/5029151-bolsonaro-rebate-lula-e-volta-a-prometer-auxilio-de-rs-600-em-2023.html https://jornalcontabil.com.br/noticia/este-sera-o-novo-valor-do-auxilio-brasil-2023-veja-agora/ https://www.camara.leg.br/noticias/973711-SANCIONADA-LEI-QUE-RECRIA-O-PROGRAMA-BOLSA-FAMILIA https://www.planalto.gov.br/ccivil_03/_ato2023-2026/2023/lei/l14601.htm
A9: F08 | B9: Flávio | C9: 00:20 | D9: Reduflação no governo Lula: dúzia de ovos virou caixa com 10, sabão em pó de 1 kg virou 800 g, barra de chocolate de 120 g virou 80 g, rolo de papel higiênico de 40 m virou 20 m. | E9: Exagerado | F9: A reduflação existe no Brasil e há casos documentados de caixas de ovos com 10 unidades, sabão em pó de 800 g e papel higiênico com menos metros. Mas é uma prática da indústria, anterior ao atual governo e que não resulta de política federal. Não encontrei os números exatos citados (chocolate de 120 g para 80 g, papel higiênico de 40 m para 20 m) como tendência geral. | G9: Média | H9: Exagerado | I9: Sim | J9: Concordo. O limite de buscas da sessão acabou, então não pude fazer busca nova. Lembro, de conhecimento prévio, que a regra federal que obriga avisar o consumidor sobre redução de quantidade (Portaria MJSP 392/2021) é de 2021, antes do atual governo. Isso reforça que a prática não começou com Lula. O link do ABCdoABC é de portal regional que repete um alerta do Procon; tem valor secundário. | K9: https://www.infomoney.com.br/?p=1885250 https://diariodonordeste.verdesmares.com.br/negocios/reduflacao-ocorre-mais-no-azeite-manteiga-e-cafe-aponta-estudo-veja-produtos-1.3531679 https://goias.gov.br/procon/wp-content/uploads/sites/19/2024/09/PLANILHA-GERAL-PESQUISA-DE-PRECOS-PRODUTOS-DE-LIMPEZA-E-HIGIENE-PESSOAL.pdf https://abcdoabc.com.br/procon-santo-andre-alerta-consumidores-sobre-reduflacao/
A10: F09 | B10: Flávio | C10: 00:19 | D10: O Brasil tem uma das maiores taxas de juros do mundo. | E10: Verdadeiro | F10: Com a Selic perto de 14,25% a 14,50% em 2026, o Brasil está entre os maiores juros nominais do mundo e em 1º ou 2º lugar em juros reais, segundo rankings citados pela imprensa econômica. | G10: Alta | H10: Verdadeiro | I10: Sim | J10: Concordo. Não consegui fazer busca nova porque o limite de buscas acabou. A afirmação é genérica ("uma das maiores") e condiz com o histórico sabido da Selic e com as reportagens citadas, que são de portais de notícias. | K10: https://www.poder360.com.br/poder-economia/mesmo-com-corte-brasil-tem-o-maior-juro-real-do-planeta/ https://www.moneytimes.com.br/selic-a-1450-brasil-segue-com-o-2o-maior-juro-real-do-mundo-mesmo-apos-corte-jcav/ https://www.poder360.com.br/poder-economia/brasil-mantem-maior-juro-real-do-mundo-diz-pesquisa/
A11: F10 | B11: Flávio | C11: 00:21 | D11: Lula chamou o agro de fascista e disse que as pessoas (do agro) têm que se ajoelhar aos seus pés. | E11: Verdadeiro, mas impreciso | F11: Em 2022, Lula disse que parte do agronegócio era "fascista e direitista" e depois afirmou que não quis generalizar. Segundo a pesquisa original, em 2026 ele também disse que o agro deveria "se ajoelhar" diante dele por causa dos recursos dados ao setor. Flávio junta as duas falas e generaliza para o agro inteiro. | G11: Média | H11: Verdadeiro, mas impreciso | I11: Sim | J11: Concordo com o veredito. A fala de 2022 sobre parte do agro ser fascista está bem documentada. Não consegui abrir a fonte da fala do "ajoelhar" (o Canal Rural bloqueou o acesso, erro 403) e o limite de buscas acabou. Por isso essa parte depende só da fonte original, o que reduz a confiança. | K11: https://www.poder360.com.br/eleicoes/lula-diz-que-nao-generalizou-ao-ligar-agro-ao-fascismo/ https://jornaldebrasilia.com.br/noticias/politica-e-poder/aliado-de-lula-no-agro-diz-que-petista-errou-e-precisa-se-desculpar-por-fala-sobre-fascismo/ https://www.canalrural.com.br/politica/tereza-cristina-rebate-lula-apos-fala-sobre-agro-isso-nao-se-faz-com-bravatas/
A12: F11 | B12: Flávio | C12: 00:24 | D12: Os juros reais do crédito do Plano Safra chegam perto de 20%, e o governo Lula contingencia recursos do seguro rural e do Plano Safra. | E12: Exagerado | F12: O bloqueio de recursos do seguro rural (PSR) em 2026 foi noticiado. Já os juros das linhas oficiais do Plano Safra 2026/27 estão bem abaixo de 20%: o Pronamp tem teto de 9% ao ano e o Pronaf é ainda mais barato. Descontada a inflação, o juro real das linhas equalizadas fica muito longe de 20%. | G12: Média | H12: Exagerado | I12: Sim | J12: Confirmei no Times Brasil e no AgFeed o teto de 9% do Pronamp e que nenhum dos dois fala em 20%. As duas reportagens não informam a taxa de 12,5% do custeio empresarial que a pesquisa original atribuiu a elas. Não consegui abrir a matéria do Canal Rural sobre o bloqueio de R$ 461,7 milhões (erro 403). O AgFeed mostra ainda que o volume de custeio caiu cerca de 11% em termos reais, o que dá alguma base à crítica de aperto no crédito. A parte dos juros de 20% continua sem sustentação para o crédito oficial. | K12: https://timesbrasil.com.br/empresas-e-negocios/agro/plano-safra-26-27-governo-eleva-credito-a-r-5251-bilhoes-e-impoe-taxa-maxima-de-juros-no-campo/ https://agfeed.com.br/economia/plano-safra-cresce-menos-que-a-inflacao-e-agricultura-empresarial-tera-menos-recursos-para-o-custeio https://www.canalrural.com.br/politica/bloqueio-de-r-4617-milhoes-no-psr-e-atribuido-a-restricoes-fiscais/ https://www.canalrural.com.br/politica/plano-safra-da-agricultura-familiar-preve-r-973-bilhoes-para-2026-2027/
... A92: L35 | B92: Lula | C92: 01:50 | D92: O governo Bolsonaro gastou cerca de 30% a mais no cartão corporativo que o governo Lula. | E92: Verdadeiro, mas impreciso | F92: Abri a matéria do Terra (24/10/2026), que é uma fonte permitida. Os números são estes: - Secretaria de Administração da Presidência: R$ 41,2 milhões com Bolsonaro (2019-2022) contra R$ 20,4 milhões com Lula (2023-2025). - Presidência, incluindo GSI e Abin: R$ 82,4 milhões contra R$ 45,2 milhões. - Governo federal inteiro: cerca de R$ 1 bilhão com Bolsonaro, em 4 anos, contra cerca de R$ 1,4 bilhão com Lula, em 3 anos. Desse total de Lula, R$ 1,1 bilhão (78%) foi para calamidades. Em valores totais, Bolsonaro gastou cerca de 82% a mais na Presidência e cerca de 102% a mais na Secretaria. Pela média anual (cálculo próprio), a diferença cai para cerca de 37% e 51%. No âmbito da Presidência, portanto, a ideia de que Bolsonaro gastou mais procede, e a média anual fica perto do '30%' citado. Há ressalvas. No governo federal inteiro, a relação se inverte e Lula gastou mais. Os valores também mudam conforme a correção pela inflação e a metodologia. O próprio Terra lembra que a CGU revisou o total de Bolsonaro para cerca de R$ 42 milhões a R$ 48 milhões. E o texto não menciona os 30%. A frase de Lula vale só para a Presidência e não diz qual recorte usou. | G92: Média | H92: Verdadeiro, mas impreciso | I92: Sim | J92: REAVALIADO SEM FONTES ENVIESADAS. O veredito não mudou. A Gazeta do Povo (excluída) foi retirada, e nenhum dado dela foi usado. Os percentuais anuais foram recalculados só com os números do Terra, e estão corretos. Revisor: Confirmei pelo WebFetch os números citados do Terra. Há uma ressalva: o Terra atribui os números da Secretaria ao Aos Fatos e os da Presidência ao Estadão Verifica, que são checagens, e não informa a fonte do total do governo federal. Ainda assim, a fonte usada é o Terra, um portal jornalístico, com dados que vêm do Portal da Transparência. Nenhuma fonte excluída foi usada. A confiança Média se justifica por essa origem indireta dos números e pela divergência de metodologias. | K92: https://www.terra.com.br/noticias/eleicoes/jair-bolsonaro-gastou-mais-no-cartao-corporativo-do-que-lula,4ffda9eadcc210176ff3273b5ac8f854m750onan.html https://portaldatransparencia.gov.br/cartoes

Sheet Promessas
A1: ID | B1: Candidato | C1: Tema | D1: Tempo no vídeo | E1: Promessa | F1: Viabilidade (%) | G1: Classificação | H1: Justificativa | I1: Custo estimado | J1: Fatores econômicos | K1: Fatores regionais | L1: Obstáculos (legais, políticos, técnicos) | M1: Confiança | N1: % análise inicial | O1: Nota do revisor independente | P1: Principais fontes | R1: Grupo do tema
A2: PF01 | B2: Flávio | C2: Infraestrutura | D2: 00:10 | E2: Concluir a Transnordestina até os portos de Suape (PE) e Pecém (CE). | F2: 0.25 | G2: =IF(F2>=0.7,"Alta",IF(F2>=0.4,"Média","Baixa")) | H2: Chegar a Pecém até 2030 é provável, mas não garantido, dado o histórico de atrasos. Terminar os cerca de 540 km até Suape em quatro anos, contratando só lotes isolados, é improvável. Como a promessa inclui os dois portos, a nota fica baixa. | I2: Não há custo total estimado para Salgueiro–Suape (cerca de 540 km). O único valor concreto é um contrato de R$ 312,8 milhões, assinado em julho de 2026, para 73,3 km entre Custódia e Arcoverde (Diário de Pernambuco). O ramal de Pecém é pago pela TLSA com recursos do FDNE. | J2: O eixo Eliseu Martins–Pecém estava cerca de 81% pronto em 2026, e o aditivo de 2022 dá prazo até por volta de 2029. Em Pernambuco, a União voltou a contratar obras em lotes (Custódia–Arcoverde), mas cada lote depende de dinheiro do orçamento, que é pouco dentro do arcabouço fiscal. | K2: Para Ceará e Piauí, a ferrovia escoa minério e grãos do MATOPIBA até o Pecém. Pernambuco e a FIEPE pressionam pelo ramal até Suape, mas a demanda de carga desse trecho é questionada desde 2022. | L2: Não exige PEC nem lei nova. Exige decisão do TCU (o ministro Jhonatan de Jesus pediu vista e a sessão foi remarcada para 14/10), definição do modelo para o trecho pernambucano, desapropriações e licenças. A obra começou em 2006, ficou parada em 2016 e já perdeu vários prazos. | M2: Média | N2: 0.3 | O2: Baixei de 30% para 25%. Ao reler a fonte, apareceu um fato que a análise original ignorou: em julho de 2026 houve contrato de R$ 312,8 milhões para 73 km no trecho pernambucano. Isso mostra que o trecho não está totalmente parado, mas também que avança em lotes pequenos, num ritmo incompatível com chegar a Suape até 2030. Também pesei o risco de atraso no próprio ramal de Pecém. Limitação: o limite de buscas da sessão acabou, então conferi lendo diretamente as fontes originais, sem fazer buscas novas. | P2: https://www.diariodepernambuco.com.br/economia/2026/10/11725523-analise-sobre-trecho-pernambucano-da-ferrovia-transnordestina-e-adiada-pelo-tcu.html https://diariodonordeste.verdesmares.com.br/negocios/transnordestina-veja-cronograma-das-obras-e-o-que-muda-com-aditivo-do-contrato-da-ferrovia-no-ce-1.3318404 https://www.diariodepernambuco.com.br/economia/2026/05/11714501-transnordestina-em-pernambuco-um-historico-de-decisoes-negativas.html https://www.diariodepernambuco.com.br/economia/2026/05/11714979-transnordestina-governo-e-empresarios-assinam-manifesto-pela-conclusao-do-trecho-salgueiro-suape.html | R2: Infraestrutura
A3: PF02 | B3: Flávio | C3: Infraestrutura / Sul | D3: 00:10 | E3: Construir o eixo sul ferroviário ligando o Centro-Oeste ao oeste do Paraná e de Santa Catarina (Nova Ferroeste). | F3: 0.05 | G3: =IF(F3>=0.7,"Alta",IF(F3>=0.4,"Média","Baixa")) | H3: Pelo próprio desenho contratual, o eixo completo não ficaria pronto antes de meados dos anos 2030, mesmo com leilão em 2027. No máximo, dá para fazer o leilão e começar as obras até 2030. | I3: R$ 35,8 bilhões para 1.567 km, incluindo material rodante, segundo o estudo de viabilidade (EVTEA). Lance mínimo de R$ 110 milhões e concessão de 99 anos (AEN-PR). | J3: O projeto depende quase todo de capital privado e ainda não tem leilão marcado. Com juros altos, é difícil financiar uma obra desse tamanho, e um aporte federal relevante não cabe no arcabouço fiscal. | K3: A ferrovia ligaria Maracaju (MS), o oeste do Paraná e Chapecó (SC) a Paranaguá, passando por 67 municípios. É uma região forte em grãos e proteína animal que hoje depende de caminhões. O traçado passa por terras indígenas no MS e pela Serra do Mar. | L3: A Licença Prévia ainda está em análise no Ibama. Depois do leilão, o projeto executivo leva cerca de 2 anos, e só então vem a Licença de Instalação. O próprio edital prevê, nos primeiros 7 anos, só o trecho Paranaguá–Guarapuava e a melhoria de Guarapuava–Cascavel. Os outros trechos só ganham cronograma depois que a operação começar. A concessão é estadual (Paraná) e envolve três estados, então a União tem pouco controle. | M3: Alta | N3: 0.08 | O3: Baixei de 8% para 5%. O edital, que a análise original não detalhou, já prevê só o primeiro trecho nos primeiros 7 anos e 2 anos de projeto executivo antes da Licença de Instalação. Isso torna a conclusão até 2030 praticamente impossível no papel. Os dados de custo da análise original foram confirmados em fonte oficial (AEN-PR). Não foi possível fazer buscas novas porque o limite da sessão acabou. | P3: https://www.parana.pr.gov.br/aen/Noticia/Perguntas-e-respostas-conheca-os-detalhes-do-edital-da-Nova-Ferroeste https://www.parana.pr.gov.br/aen/Noticia/Estado-divulga-o-edital-da-Nova-Ferroeste-ligacao-ferroviaria-que-vai-transformar-o https://www.campograndenews.com.br/economia/para-estudos-de-terra-indigena-em-ms-leilao-da-nova-ferroeste-ficara-para-2025 https://www.semadesc.ms.gov.br/?p=120681 | R3: Infraestrutura
A4: PF03 | B4: Flávio | C4: Infraestrutura / Centro-Oeste | D4: 00:11 | E4: Concluir a FICO (Ferrovia de Integração Centro-Oeste) e a FIOL (Ferrovia de Integração Oeste-Leste). | F4: 0.12 | G4: =IF(F4>=0.7,"Alta",IF(F4>=0.4,"Média","Baixa")) | H4: FICO 1 e FIOL II podem ficar prontas até 2030. Mas o próprio governo fala em 2033 para a FIOL 1 e em 2037–2038 para o corredor completo, o que torna a conclusão das duas ferrovias no mandato muito improvável. | I4: Parcial: FIOL 1 com Porto Sul custa cerca de R$ 7 bilhões, segundo o ministro dos Transportes (Agência Infra). O lote 05FC da FIOL II custa R$ 467,9 milhões. A FICO 1 é paga pela Vale como contrapartida da renovação da EFVM. FIOL 3 e FICO 2 não têm orçamento. | J4: A FIOL II tinha cerca de 71% de execução física, e o governo prevê leiloá-la. A FIOL 1 deve passar da Bamin, que está inadimplente, para a Mota-Engil, com entrega prevista para 2033. A extensão da FICO 2 até Lucas do Rio Verde é investimento não obrigatório e depende de acordo com a operadora. Segundo o ministro, o corredor inteiro só fica pronto entre 2037 e 2038. | K4: O eixo atende o oeste da Bahia, o norte de Goiás e o leste de Mato Grosso, regiões de grãos e minério, e daria saída pelo Porto Sul (Ilhéus) com ligação à Norte-Sul. | L4: Depende da troca de concessionário com aval da ANTT, do leilão da FIOL II, de projeto e licenças da FIOL 3 (cerca de 900 km), de auditorias do TCU (contrato do Lote 5F encerrado com 64,66% executado) e de acordo com a Vale para a FICO 2. Não exige PEC. | M4: Média | N4: 0.15 | O4: Baixei de 15% para 12%. A mesma fonte usada pela análise original traz a previsão oficial de conclusão do corredor inteiro entre 2037 e 2038, que a análise não usou. Ela também diz que a FICO 2 é investimento não obrigatório e que a FIOL 3 só começa depois da FIOL 2. Sem buscas novas, porque o limite da sessão acabou. | P4: https://agenciainfra.com/blog/mota-engil-aguarda-autorizacao-da-antt-para-assumir-fiol-1-diz-ministro/ https://static.poder360.com.br/uploads/2026/10/001.733-2026-5-ASC-auditoria_Fiol_Lote-5F.pdf https://www.bnews.com.br/noticias/politica/governo-lanca-edital-de-meio-bilhao-para-concluir-obras-da-fiol-na-bahia.html https://www.gov.br/transportes/pt-br/assuntos/incentivos/incentivos-fiscais/reidi-requerimento-e-consulta/Portarian502de27abr2021ValecFIOLReidiDOU29abr2021.pdf | R4: Infraestrutura
A5: PF04 | B5: Flávio | C5: Infraestrutura | D5: 00:10 | E5: Ampliar concessões de rodovias com pedágio zero para motocicletas em todas elas, e continuar concessões de portos. | F5: 0.45 | G5: =IF(F5>=0.7,"Alta",IF(F5>=0.4,"Média","Baixa")) | H5: Continuar as concessões é quase certo, e a isenção nas concessões federais novas é factível. Isentar motos em todas as rodovias, incluindo contratos vigentes e rodovias estaduais, esbarra em contratos e na divisão de competências. A frase da promessa é ambígua e pode se referir só às novas concessões, o que a deixaria no meio da faixa. | I5: Não estimável. Isentar motos nos contratos já em vigor exige reequilíbrio econômico-financeiro, com aumento da tarifa dos outros veículos, mais prazo de concessão ou compensação da União. O impacto depende da participação das motos na receita de cada praça. | J5: As concessões de rodovias e portos seguiram em governos de linhas diferentes, então essa parte é muito viável. A isenção geral não tem lei aprovada. O PL 312/2026, do senador Cleitinho (Republicanos/MG), prevê isenção em todas as rodovias, mas está 'aguardando despacho' desde 04/02/2026. | K5: A medida é nacional, com peso maior no Sul e no Sudeste, onde se concentram as rodovias pedagiadas. Beneficia motociclistas de entrega e quem usa a moto para ir trabalhar. | L5: Nas concessões federais novas, basta prever a isenção no edital. Nos contratos vigentes, é preciso lei ou renegociação com reequilíbrio, com risco de disputa judicial. Rodovias estaduais concedidas são de competência dos estados. Leilões de portos dependem da ANTAQ e do TCU. | M5: Média | N5: 0.45 | O5: Mantive 45%. Confirmei no site do Senado que o PL 312/2026 é do senador Cleitinho e está aguardando despacho desde fevereiro de 2026. A fonte da ALMT usada na análise original não foi verificada. A ambiguidade da promessa ('todas elas' pode significar só as novas concessões) foi registrada, mas não muda a nota. Sem buscas novas, porque o limite da sessão acabou. | P5: https://www25.senado.leg.br/web/atividade/materias/-/materia/172564 https://www12.senado.leg.br/ecidadania/visualizacaomateria?id=172564 https://www.al.mt.gov.br/storage/webdisco/cp/20260615104430170100.pdf | R5: Infraestrutura
A6: PF05 | B6: Flávio | C6: Infraestrutura / Conectividade | D6: 00:10 | E6: Tratar internet como infraestrutura e levar conexão a escolas, unidades de saúde e aldeias indígenas, inclusive para agricultura de precisão. | F6: 0.62 | G6: =IF(F6>=0.7,"Alta",IF(F6>=0.4,"Média","Baixa")) | H6: Escolas e unidades de saúde devem avançar bastante até 2030. Mas a meta anterior (2026) foi perdida, o ritmo de cerca de 5 mil escolas por ano teria de dobrar, e a parte de aldeias e agricultura de precisão tende a ficar parcial. Por isso a nota fica no alto da faixa Média, e não na Alta. | I6: Cerca de R$ 8,8 a 9 bilhões na Estratégia Nacional de Escolas Conectadas, dos quais cerca de R$ 6,5 bilhões vêm do Novo PAC. Há também recursos do Fust e obrigações do leilão do 5G. O MME leva energia, via PAC, às escolas que não têm. Fontes: MCom/MEC, citados pela imprensa. | J6: É uma política já em andamento e paga em boa parte por fundos setoriais e obrigações das operadoras. Mas a meta oficial era conectar as 138,3 mil escolas até 2026, e só cerca de 99 mil estavam conectadas em 2026 (eram cerca de 94 mil em 2025). Ou seja, a meta foi descumprida e o ritmo foi de cerca de 5 mil escolas por ano. | K6: As maiores lacunas estão no Norte (20,4 mil escolas na meta; no Acre, menos da metade conectada) e no Nordeste rural (49,9 mil escolas). Aldeias dependem de satélite e, às vezes, de levar energia primeiro. A cobertura 4G/5G no campo para agricultura de precisão ainda é baixa. | L6: Não exige mudança na lei. Exige coordenação entre MEC, MCom, MME, estados e municípios, logística na Amazônia, contratos de manutenção e pagamento contínuo do serviço. A cobertura rural depende do calendário de obrigações do 5G. | M6: Média | N6: 0.72 | O6: Baixei de 72% para 62%, saindo da faixa Alta para a Média. A fonte original (2023) mostra que a meta era universalizar o acesso nas escolas até 2026, e isso não aconteceu. Esse histórico de execução foi ignorado pela análise original e, pela mesma régua usada nas ferrovias, pesa contra a nota. Para cumprir até 2030, o ritmo teria de dobrar. Sem buscas novas, porque o limite da sessão acabou. | P6: https://www.itatiaia.com.br/politica/governo-federal-lanca-escolas-conectadas-meta-e-ter-1388-mil-escolas-publicas-com-internet-de-qualidade-ate-2026/ https://brasil61.com/n/internet-chega-a-quase-metade-das-escolas-publicas-do-acre-mcom260240 https://brasil61.com/n/internet-chega-a-mais-da-metade-das-escolas-publicas-do-amazonas-mcom260243 https://www.conexaoto.com.br/2026/04/11/tocantins-supera-70-das-escolas-publicas-conectadas-a-internet | R6: Infraestrutura
A7: PF06 | B7: Flávio | C7: Economia / Renda | D7: 00:28 | E7: Reajustar salário mínimo, aposentadorias, BPC e aposentadoria rural acima da inflação, e não privatizar Banco do Brasil, Caixa e Petrobras. | F7: 0.68 | G7: =IF(F7>=0.7,"Alta",IF(F7>=0.4,"Média","Baixa")) | H7: Para cumprir o núcleo da promessa (mínimo, BPC e aposentadoria rural acima da inflação e não privatizar) basta manter o que já existe, e Flávio reafirmou isso na sabatina de 16/10. Ele também disse que manterá o ganho real para aposentados 'como ocorre hoje', o que limita a promessa ao piso. O risco que resta é a pressão fiscal pela desindexação e a leitura ampla de 'todas as aposentadorias'. | I7: Cada R$ 1 a mais no salário mínimo custa cerca de R$ 413 milhões por ano (PLOA 2027, segundo SBT News, que cita o Ministério da Fazenda). O PLOA 2027 prevê mínimo de R$ 1.741, alta de R$ 120 (7,4%) sobre os R$ 1.621 atuais. Manter a regra atual não cria custo além do que já está projetado. Dar ganho real a todas as aposentadorias acima do piso seria custo novo de dezenas de bilhões por ano; não estimado oficialmente. | J7: O PLOA 2027 prevê receita líquida de R$ 2,849 trilhões e despesa de R$ 2,83 trilhões. A meta de primário é de R$ 73,2 bilhões, e o governo projeta R$ 83,4 bilhões após deduções. A regra atual (Lei 14.663/2023, com limite de 0,6% a 2,5% de ganho real fixado pela Lei 15.077/2024) já garante ganho real ao piso e aos benefícios vinculados a ele. A fonte de 'mais de R$ 200 bilhões por ano' que Flávio citou é a securitização de créditos da União (O Liberal, 16/10/2026). Essa receita é financeira e não amplia o limite de despesa do arcabouço. | K7: O alcance é nacional, mas o peso é maior no Nordeste, no Norte e nos municípios pequenos, onde BPC e aposentadoria rural de um salário mínimo são parte central da renda local. | L7: Manter a regra atual não exige nada, e não privatizar BB, Caixa e Petrobras depende só do Executivo. A pressão crescente da regra do mínimo sobre a Previdência e o BPC, num quadro de discricionárias espremidas, pode levar o próximo governo a rever a indexação, e o mercado cobra isso. Ganho real para todas as aposentadorias exigiria lei e espaço no teto. | M7: Média | N7: 0.62 | O7: Subi de 62 para 68. A análise original tratou os 'R$ 200 bilhões' como um ajuste de corte de gastos que entraria em choque com a promessa. Segundo O Liberal, porém, o valor é receita prometida com securitização de créditos da União, não corte. Na mesma sabatina, Flávio se comprometeu a manter o ganho real dos aposentados 'como ocorre hoje' e disse que não vai desvincular. Com isso, a promessa se aproxima de manter o que já existe e o choque com a promessa fiscal fica menor do que o original afirmou. Fiz uma correção: a fonte SBT não menciona aposentadorias nem BPC e não traz o R$ 200 bi. Também não consegui confirmar a afirmação de que ele evitou o compromisso em agosto. Fica em Média, no limite da faixa, porque a indexação deve sofrer pressão fiscal até 2030. | P7: https://www.congressoemfoco.com.br/noticia/121825/projeto-de-orcamento-de-2027-preve-salario-minimo-de-r-1-741 https://www.oliberal.com/politica/flavio-diz-que-nao-vai-desvincular-reajuste-do-minimo-e-nem-alterar-pisos-de-saude-e-educacao-1.1183567 https://sbtnews.sbt.com.br/noticia/eleicoes/flavio-promete-reajuste-do-minimo-acima-da-inflacao https://sbtnews.sbt.com.br/noticia/politica/salario-minimo-de-2027-sera-de-r-1-741-diz-durigan | R7: Economia
A8: PF07 | B8: Flávio | C8: Mobilidade | D8: 00:17 | E8: Apoiar tarifa zero nos ônibus nos fins de semana. | F8: 0.3 | G8: =IF(F8>=0.7,"Alta",IF(F8>=0.4,"Média","Baixa")) | H8: A proposta não tem fonte de financiamento nem instrumento legal definidos, gera custo bilionário recorrente dentro do arcabouço e a competência é municipal. A adesão de Flávio é recente e genérica, então uma tarifa zero nacional nos fins de semana até 2030 é pouco provável. | I8: De R$ 12 bilhões por ano (governo) a R$ 20,8 bilhões por ano (NTU, Diário do Transporte e DGABC). O deputado Jilmar Tatto estima R$ 16 bilhões por ano, cerca de 26% dos R$ 61 bilhões em emendas de 2026 (Congresso em Foco). | J8: Seria uma despesa nova e permanente, que teria de caber no teto do arcabouço, num PLOA 2027 já apertado. Flávio não indicou fonte de financiamento. A PEC de Lula financia a medida com emendas parlamentares, e para o Congresso isso custa poder político. | K8: O transporte coletivo é competência municipal (art. 30, V, da CF). As experiências de tarifa zero existentes estão concentradas em municípios pequenos e médios. Nas metrópoles do Sudeste o custo por município é muito maior e há contratos de concessão em vigor. | L8: Uma fonte federal permanente exige PEC (308 votos na Câmara e 49 no Senado, em dois turnos) ou lei com fonte definida e repasse aos municípios. Os contratos de concessão precisariam ser reequilibrados. 'Apoiar' é um compromisso fraco: se a medida não sair, fica difícil responsabilizar o candidato. | M8: Média | N8: 0.32 | O8: Baixei de 32 para 30 e mantive na faixa Baixa. Confirmei o custo (R$ 16 bi por ano, 26% das emendas) e o quórum da PEC no Congresso em Foco. Não consegui confirmar duas afirmações do original: que o presidente da Câmara 'já resiste' e que a PEC foi enviada em 21/10 (a reportagem de 15/10 diz que o texto ainda não tinha sido apresentado). Por isso não as usei como base. O pequeno ajuste para baixo vem de dois pontos: falta qualquer fonte de financiamento proposta por Flávio e o verbo 'apoiar' é fraco. Para ser coerente, a mesma promessa de Lula deve ser avaliada com o mesmo obstáculo de PEC e financiamento. | P8: https://www.congressoemfoco.com.br/noticia/123316/lula-propoe-usar-emendas-para-financiar-tarifa-zero-aos-fins-de-semana https://diariodotransporte.com.br/2026/10/16/tarifa-zero-aos-fins-de-semana-pode-custar-r-208-bilhoes-por-ano-calcula-ntu/ https://www.dgabc.com.br/Noticia/4354042/tarifa-zero-governo-preve-r$-12-bi-mas-setor-estima-r$-20-8-bi https://timesbrasil.com.br/brasil/lula-diz-que-enviara-pec-da-tarifa-zero-ao-congresso-nesta-quarta-21-custo-pode-atingir-r-16-bilhoes-anuais/ | R8: Mobilidade
A9: PF08 | B9: Flávio | C9: Agro / Centro-Oeste | D9: 00:24 | E9: Aprovar lei que proíba contingenciar recursos do seguro rural e do Plano Safra; dar previsibilidade e segurança jurídica ao agro; digitalizar a concessão da aposentadoria rural. | F9: 0.64 | G9: =IF(F9>=0.7,"Alta",IF(F9>=0.4,"Média","Baixa")) | H9: A blindagem legal tem custo baixo, base parlamentar forte e precedente, e a digitalização é administrativa. A blindagem só pelo contingenciamento, porém, pode não evitar os bloqueios do arcabouço, que foi o que cortou o PSR em 2026, e a parte de 'segurança jurídica' é vaga. Por isso fica na faixa média-alta, e não na Alta. | I9: Blindar o PSR custa pouco no total: o bloqueio de 2026 foi de cerca de R$ 518 milhões (R$ 461,7 milhões mais R$ 56 milhões), e o setor pede cerca de R$ 4 bilhões por ano. A equalização de juros do Plano Safra, que tem R$ 525 bilhões em crédito no ciclo 2026/27, custa bilhões por ano. Digitalizar a aposentadoria rural tem custo baixo. | J9: Excluir essas despesas dos cortes não aumenta o teto do arcabouço (LC 200/2023), só transfere o corte para outras discricionárias. É preciso distinguir dois mecanismos. O contingenciamento (art. 9 da LRF) responde a frustração de receita. O bloqueio responde ao limite de despesa do arcabouço. Os cortes do PSR em 2026 foram atribuídos a 'restrições fiscais', e uma lei que proíba só o contingenciamento pode não impedir o bloqueio. | K9: O Centro-Oeste (MT, GO, MS) e o Sul (RS, PR) concentram a demanda por seguro rural e crédito. No Sul as perdas climáticas se repetem, e o agro goiano reclamou de menos crédito no ciclo 2026/27. | L9: Mexer na LRF exige lei complementar (maioria absoluta: 257 deputados e 41 senadores). A Frente Parlamentar da Agropecuária (FPA) tem base ampla e há precedente: a LC 177/2021 blindou o FNDCT. Para valer de fato, a proteção teria de alcançar também o bloqueio pelo teto, e a equipe econômica resistiria. 'Previsibilidade e segurança jurídica' não é mensurável. A digitalização depende do INSS, que já usa autodeclaração e CNIS rural, então a promessa é em parte algo já em curso. | M9: Média | N9: 0.7 | O9: Baixei de 70 para 64 e passei de Alta para Média por três motivos. Primeiro, a análise original não distinguiu contingenciamento (LRF) de bloqueio (teto do arcabouço), e foi o bloqueio que atingiu o PSR em 2026. Uma lei que proíba só o contingenciamento pode deixar a promessa sem efeito. Segundo, não consegui confirmar a tramitação do projeto de Tereza Cristina citado no original: a busca estava sem saldo e o site do Canal Rural retornou erro 403. Terceiro, descartei a fonte cnabrasil.org.br, que é de entidade de classe, não é oficial nem jornalística. | P9: https://www.canalrural.com.br/politica/bloqueio-de-r-4617-milhoes-no-psr-e-atribuido-a-restricoes-fiscais/ https://comprerural.com/governo-bloqueia-mais-r-56-milhoes-do-seguro-rural-as-vesperas-do-plano-safra-2026-27/ https://www.jornalopcao.com.br/ultimas-noticias/plano-safra-2026-2027-anuncia-r-525-bilhoes-agro-de-goias-ve-reducao-do-credito-e-cobra-seguro-rural-842176/ https://cnabrasil.org.br/noticias/sistema-faep-pede-r-670-bilhoes-no-plano-safra-2026-27 | R9: Agro
A10: PF09 | B10: Flávio | C10: Segurança / Fronteiras | D10: 00:25 | E10: Fazer pacto com governadores do Centro-Oeste contra o crime organizado e as rotas de tráfico nas fronteiras. | F10: 0.68 | G10: =IF(F10>=0.7,"Alta",IF(F10>=0.4,"Média","Baixa")) | H10: O núcleo da promessa é firmar um pacto com governadores. Isso cabe ao Executivo, tem precedentes e conta com governadores motivados pela escalada da violência na fronteira de MS. A probabilidade de cumprimento formal é alta. Reduzi a nota de 72 para 68 (limite superior da faixa Média) porque 'substancialmente cumprida' supõe ação contínua contra as rotas. O plano associado (força militar de fronteira, dobrar o investimento) não tem financiamento definido, e a PEC da Segurança está parada no plenário do Senado. Também não encontrei, nas fontes abertas, o pacto com governadores do Centro-Oeste citado como item do plano de Flávio: a reportagem do Correio do Estado sobre as propostas de fronteira não fala em 'pacto'. | I10: Baixo para formalizar o pacto, que é um acordo político e administrativo. Para operar de fato (Ficco, inteligência integrada, efetivo da PF/PRF/Forças Armadas na faixa de fronteira, tecnologia de vigilância), algumas centenas de milhões a poucos bilhões de reais por ano. A 'força de elite' de fronteira que o plano de Flávio propõe e a promessa de dobrar o investimento federal em segurança em quatro anos ficariam bem acima disso, e o candidato não indicou de onde viria o dinheiro. | J10: É despesa discricionária disputada dentro do arcabouço fiscal. Segundo o Correio do Estado (19/10/2026), Flávio cita dados da Fazenda de que a União destina 0,4% dos gastos à segurança e promete dobrar o investimento sem detalhar as fontes. O FNSP, as emendas e a estrutura federal já existente (programa Brasil Contra o Crime Organizado, lançado em maio de 2026, e as Ficco) dão base para operações conjuntas sem lei nova. | K10: MS e MT fazem fronteira com Paraguai e Bolívia. Segundo o Correio do Estado (out/2026), a fronteira sul-mato-grossense vive uma guerra crescente entre CV e PCC pelo controle do tráfico, o que deixa os governadores interessados em cooperar. GO e DF funcionam como corredores logísticos. Os governadores eleitos em 2026 tomam posse junto com o presidente, e o alinhamento político da região tende a favorecer um pacto com um governo do PL. | L10: Pelo art. 144 da CF, a segurança pública é sobretudo dos estados: a União coordena, mas não comanda as polícias estaduais. A PEC 18/2025, que reforçaria a coordenação federal, foi aprovada na CCJ do Senado, mas a votação em plenário saiu da pauta (Correio do Estado, 19/10/2026). Faltam efetivo e continuidade orçamentária. Iniciativas anteriores para a fronteira (ENAFRON, PEF, PPIF) tiveram resultados limitados. Assinar o pacto é fácil; o difícil é reduzir as rotas de forma mensurável. | M10: Média | N10: 0.72 | O10: RECHECADO (2ª rodada). Fiz só 1 das 3 buscas planejadas: o limite de buscas da sessão (200, compartilhado entre os agentes) acabou nas consultas seguintes. Abri e confirmei três páginas: Correio do Estado (19/10/2026), Reuters via Internazionale (18/06/2026) e CNN Brasil (28/05/2026). Fatos novos de 2026 que o agente original não tinha: o programa Brasil Contra o Crime Organizado (maio de 2026), a situação da PEC 18/2025 (aprovada na CCJ, retirada da pauta do plenário pelo presidente do Senado), o plano de Flávio com força de elite de fronteira e a meta de dobrar o investimento sem fonte indicada, e a escalada CV x PCC em MS. A nota cai 4 pontos, de Alta para Média, porque a promessa depende de financiamento não especificado e a PEC está travada. Não consegui abrir páginas oficiais da Câmara/Senado (proposição errada ou domínio inacessível). | P10: https://correiodoestado.com.br/cidades/conflito-na-fronteira-ocupa-espaco-entre-as-propostas-dos-candidatos-a/475016/ https://www.internazionale.it/ultime-notizie-reuters/2026/06/18/brazil-s-flavio-bolsonaro-pitches-crime-crackdown-to-boost-presidential-bid https://www.cnnbrasil.com.br/politica/grande-dia-diz-flavio-apos-eua-classificarem-pcc-e-cv-como-terroristas/ | R10: Segurança
A11: PF10 | B11: Flávio | C11: Sul / RS | D11: 00:31 | E11: Ajudar o RS a sair da dívida com a União e financiar bombas d'água e comportas contra enchentes em Porto Alegre e região. | F11: 0.43 | G11: =IF(F11>=0.7,"Alta",IF(F11>=0.4,"Média","Baixa")) | H11: A parte das obras (bombas, comportas, diques) é viável até 2030. O custo é pequeno perto do orçamento federal, e em jul/2024 a União liberou R$ 6,5 bilhões para macrodrenagem no RS, dos quais R$ 2 bilhões para a Região Metropolitana de Porto Alegre. A execução, porém, está atrasada: um ano depois esses recursos não tinham sido usados e uma licitação fracassou. 'Ajudar a sair da dívida' tende a se resumir a implementar o Propag, que o RS já pediu. Quitar ou eliminar uma dívida de R$ 106,5 bilhões até 2030 é inviável. A média das duas partes fica na faixa média. As fontes OK confirmam os dados centrais. | I11: A dívida do RS com a União é de R$ 106,5 bilhões. O Estado pediu abatimento de 20% (cerca de R$ 21 bilhões), pago com cessão de FPE futuro (R$ 12,8 bilhões entre 2032 e 2055), recebíveis do FNDR (R$ 6,6 bilhões entre 2029 e 2055) e crédito da Corsan (R$ 1,8 bilhão). A Prefeitura orça em R$ 401 milhões os reparos do sistema de Porto Alegre. Há ainda R$ 2 bilhões federais destinados à RMPA para diques, comportas e bombas. | J11: O RS pediu adesão ao Propag (LC 212/2025), no 'pacote 1', com juro real zero. O saldo segue corrigido monetariamente, e parte da correção vai ao Fundo de Equalização Federativa e a investimentos no Estado. A Sefaz-RS projeta economia de R$ 42 bilhões nominais até 2057. O Tesouro calcula que o RS deixaria de pagar R$ 45 bilhões entre 2027 e 2035, e que o estoque, que poderia chegar a R$ 140 bilhões, cairia para R$ 112 bilhões. Os pagamentos estão suspensos até 2027 por causa das enchentes (cerca de R$ 14 bilhões poupados), e até lá o RS está dispensado de aportes ao Fundo. Perdoar ou quitar a dívida teria custo fiscal alto para a União e abriria precedente para outros estados. Financiar bombas e comportas é barato em comparação. | K11: O sistema de Porto Alegre foi projetado na década de 1970 e tem 68 km de diques, 23 casas de bombas e 14 comportas. Na enchente de 2024, 19 das 23 casas de bombas foram desligadas. Dos 309 equipamentos públicos destruídos, 278 estão em funcionamento, segundo a Prefeitura. Um ano depois, a licitação para elevar os painéis elétricos tinha fracassado, a obra dos diques estava parada em trechos com famílias morando em cima, e as comportas 11 a 14 ainda eram fechadas com sacos de areia e argila. Eldorado do Sul só tem planejado um dique de quase 9 km. | L11: Tirar o RS da dívida além do Propag exige lei complementar e tratamento isonômico entre os estados, o que enfrenta resistência federativa e fiscal. As obras anticheias são executadas por estado e município e dependem de projeto, licitação (uma já fracassou), reassentamento de famílias e licenciamento. O histórico recente é de atraso. | M11: Alta | N11: 0.43 | O11: REAVALIADO SEM FONTES ENVIESADAS. A viabilidade (43%) e a confiança se mantêm. Ajustes de precisão em relação ao texto do outro agente: (1) o sistema foi 'projetado' nos anos 1970, como diz a Prefeitura, e não 'começou a ser construído'; (2) foram retirados dois dados que não aparecem em nenhuma fonte OK: o juro real anterior de 4% e a adesão ficta até maio/2027; (3) 278 equipamentos 'estão em funcionamento', e não 'voltam a funcionar'; (4) os R$ 6,5 bilhões e os R$ 2 bilhões não usados vêm do Poder360, e não do SBT. Revisor: Abri as cinco fontes OK. O Governo do RS confirma a dívida de R$ 106,5 bilhões, os 20%, o FPE, o FNDR, a Corsan e os R$ 42 bilhões. A Folha PE confirma os R$ 45 bilhões entre 2027 e 2035 e a dispensa de aportes até 2027. O SBT confirma 19 de 23 casas de bombas desligadas, a licitação fracassada, os diques parados por famílias e o dique de 9 km em Eldorado. O Poder360 confirma os sacos de areia e os R$ 2 bilhões de um total de R$ 6,5 bilhões sem uso. A Prefeitura confirma os R$ 401 milhões, os números 309/278 e os 68 km, 23 casas de bombas e 14 comportas. | P11: https://estado.rs.gov.br/governo-do-estado-encaminha-a-uniao-pedido-de-adesao-ao-propag https://prefeitura.poa.br/gp/noticias/prefeito-reafirma-pedido-de-recursos-do-estado-para-obras-de-protecao-contra-cheias https://www.folhape.com.br/economia/ceron-esclarece-que-rs-esta-dispensado-de-aportes-a-fundo-do-propag/386185/ https://sbtnews.sbt.com.br/noticia/brasil/sistema-anticheias-de-porto-alegre-tem-obras-paralisadas-um-ano-apos-a-tragedia | R11: Sul
A12: PF11 | B12: Flávio | C12: Sul / Segurança | D12: 00:32 | E12: Colocar a Marinha (tropa de elite) no Porto de Paranaguá para combater o tráfico de armas e drogas. | F12: 0.65 | G12: =IF(F12>=0.7,"Alta",IF(F12>=0.4,"Média","Baixa")) | H12: Mandar a Marinha para Paranaguá é ato do Executivo (LC 97/1999, por GLO ou por atribuições subsidiárias), custa pouco e não depende do Congresso. Por isso, a parte formal é bastante viável. O mais provável, porém, é uma presença temporária ou um reforço do patrulhamento naval, sem virar uma operação permanente que reduza o tráfico de forma mensurável. O tráfico pelo porto depende sobretudo de contêineres e cargas, que são fiscalizados por PF e Receita. As fontes permitidas sustentam o diagnóstico. | I12: Baixo a moderado. Estimativa própria, sem número oficial: de dezenas a poucas centenas de milhões de reais por ano em diárias, logística e embarcações da Marinha e dos Fuzileiros Navais, pagos com o orçamento discricionário da Defesa. | J12: Paranaguá é rota de saída de cocaína. Em nov/2025, as Polícias Civil e Militar do PR apreenderam 1,2 tonelada que, segundo a polícia, iria para a Europa em navios pelo porto. Em 2023, a Operação Woodpecker (PF e Receita) ligou ao porto mais de 3 toneladas escondidas em cargas de madeira para exportação. O custo da medida é pequeno, mas disputa espaço com as despesas discricionárias da Defesa, que estão comprimidas. | K12: A cocaína sai principalmente escondida em cargas de exportação, e há casos de droga içada por mergulhadores nos navios. Desde out/2020, PF (Nepom) e PM (Patrulha Costeira) fazem patrulha marítima conjunta com lanchas na Baía de Paranaguá e entre o continente e as ilhas. A Marinha não participava dessa patrulha, mas o grupo pretendia incluí-la. A Marinha já atua localmente como Autoridade Marítima. | L12: Para a Marinha atuar em segurança pública é preciso um decreto de GLO (art. 142 da CF e LC 97/1999), que é temporário e excepcional. A alternativa é usar as atribuições subsidiárias da Marinha no patrulhamento naval. A repressão ao tráfico em cargas depende sobretudo de PF e Receita, com inteligência e escaneamento. As Forças Armadas costumam resistir a missões policiais permanentes. A medida não depende do Congresso. | M12: Média | N12: 0.65 | O12: REAVALIADO SEM FONTES ENVIESADAS. A viabilidade (65%) e a confiança se mantêm. Ajustes de precisão: (1) a Agência Brasil não cita a Europa como destino da Operação Woodpecker, só 'exterior'; o destino Europa vem da Band B, no caso de 2025; (2) a patrulha conjunta é de PF e PM, começou em 2020 e a Marinha não participava, segundo a Portos do Paraná. Foi mantida a retirada dos dados da Gazeta do Povo e do O Antagonista e da menção ao alinhamento político do governo estadual. Revisor: Abri as quatro fontes. A Band B confirma 1,2 tonelada, Polícia Civil e PM, destino Europa em navios e data de 11/11/2025. A Agência Brasil confirma a Woodpecker (PF e Receita), mais de 3 toneladas, madeira e Paranaguá, mas não fala em Europa. A Portos do Paraná confirma a patrulha PF+PM com lanchas desde 2020, sem a Marinha. A LC 97/1999 sustenta a parte legal. Não há resíduo de fonte excluída. | P12: https://www.bandab.com.br/seguranca/policia-apreende-mais-de-1-tonelada-de-cocaina-em-paranagua/amp/ https://www.planalto.gov.br/ccivil_03/leis/lcp/lcp97.htm https://agenciabrasil.ebc.com.br/geral/noticia/2023-07/pf-mira-quadrilha-que-enviava-cocaina-em-carga-madeira https://www.portosdoparana.pr.gov.br/Noticia/Acao-conjunta-intensifica-patrulha-maritima-na-regiao-dos-portos | R12: Sul
A13: PF12 | B13: Flávio | C13: Norte / Saneamento | D13: 00:35 | E13: Garantir a meta do Marco do Saneamento (90%+ de cobertura até 2033) e fazer o maior programa de saneamento da história de Belém. | F13: 0.25 | G13: =IF(F13>=0.7,"Alta",IF(F13>=0.4,"Média","Baixa")) | H13: A União tem poucos instrumentos diretos e parte de uma base muito baixa. Sair de cerca de 20% para perto de 90% de esgoto até 2030 é improvável. Um programa federal grande para Belém, via crédito e apoio à concessão, é possível, mas não basta para 'garantir' a meta. | I13: Vários bilhões de reais só para universalizar o esgoto em Belém, provavelmente entre R$ 5 e 10 bilhões, numa ordem de grandeza não oficial. O país precisa de mais de R$ 500 bilhões até 2033, segundo estimativas setoriais. Não estimável com precisão. | J13: Pelo Marco Legal (Lei 14.026/2020), o investimento vem principalmente de concessões e PPPs. O papel da União fica no crédito (FGTS, BNDES) e em transferências discricionárias limitadas pelo arcabouço fiscal. Um 'maior programa da história' pode ser financiado sobretudo pelo setor privado, o que torna essa parte mais factível do que a meta de cobertura. | K13: Belém aparece entre os piores municípios do ranking Trata Brasil, com cerca de 19 a 25% de coleta de esgoto e menos de 30% de tratamento. A cidade tem áreas de baixada alagáveis e palafitas, onde a rede custa mais e demora mais para ser implantada. | L13: A titularidade do saneamento é municipal ou regional, com o estado do Pará e a Cosanpa ou concessionárias, não da União. A meta é de 2033, depois do mandato. As obras de esgoto em área densa e alagável exigem licenciamento, desapropriações e muitos anos. O histórico nacional é de avanço lento. | M13: Média | N13: 0.25 | O13: Mantive 25%. Os dados de cobertura vêm de imprensa regional e nacional e são coerentes entre si. A régua é a mesma que vale para promessas de competência subnacional com meta posterior a 2030. Retirei das fontes a matéria da InfoMoney sobre Santarém e a do Brasil61 sobre outras capitais, que não tratam de Belém. Ponto que o original deixou de lado: a concessão regional de água e esgoto do Pará pode ampliar muito o investimento privado e tornar mais plausível a parte do 'maior programa'. Não consegui confirmar os termos dessa concessão porque a cota de buscas da sessão acabou, por isso não mudei a nota. | P13: https://www.oliberal.com/belem/belem-esta-entre-os-20-piores-municipios-em-saneamento-no-pais-aponta-trata-brasil-1.1124810 https://www.band.com.br/bandnews-fm/noticias/capital-da-cop-30-e-uma-das-ultimas-colocadas-no-ranking-de-saneamento-e-piora-situacao-em-2025-202507151206 https://www.planalto.gov.br/ccivil_03/_ato2019-2022/2020/lei/l14026.htm https://www.infomoney.com.br/brasil/paradisiaca-santarem-no-para-e-a-cidade-brasileira-com-o-pior-saneamento-basico/ | R13: Norte
... A41: PL13 | B41: Lula | C41: Norte / Meio ambiente | D41: 00:38 | E41: Ampliar a economia verde e o Fundo Amazônia, gerando mais renda com a floresta em pé e protegendo terras indígenas. | F41: 0.6 | G41: =IF(F41>=0.7,"Alta",IF(F41>=0.4,"Média","Baixa")) | H41: A meta é vaga e já está em curso, com financiamento externo e baixo custo fiscal, o que favorece o cumprimento ao menos parcial. Os limites são a execução lenta, a dependência de doadores e o conflito político sobre terras indígenas. | I41: Os recursos são majoritariamente de doações não reembolsáveis. O portal do Fundo Amazônia, consultado nesta revisão, mostra R$ 5,97 bilhões aprovados e R$ 2,93 bilhões desembolsados em 156 projetos. O impacto no Tesouro é baixo. | J41: O Fundo foi reativado em 2023 com novos doadores, e o TFFF foi lançado na COP30 em Belém, em 2025. A queda do desmatamento pelo Prodes favorece a captação. A execução é lenta: o desembolsado é cerca de 49% do aprovado. | K41: Amazônia Legal: renda per capita abaixo da média nacional, pressão do garimpo ilegal, da grilagem e da pecuária. A bioeconomia ainda é pequena diante da agropecuária regional. | L41: Depende de doadores externos (os EUA recuaram em 2025), da capacidade de execução de estados e ONGs, do conflito sobre o marco temporal (Lei 14.701/2023 e STF), do ritmo lento das demarcações e de um Congresso com forte bancada ruralista. | M41: Média | N41: 0.6 | O41: Confirmei no portal oficial os números do Fundo citados pelo original (R$ 5,97 bi aprovados, R$ 2,93 bi desembolsados, 156 projetos). Mantenho 60%: é uma meta vaga de 'ampliar', com mecanismo já existente e custo fiscal baixo, e uso a mesma régua que nas promessas genéricas do adversário. Não consegui atualizar dados de novos aportes em 2026 porque a cota de buscas acabou. | P41: https://www.fundoamazonia.gov.br/pt/home/ http://terrabrasilis.dpi.inpe.br/ https://www.bndes.gov.br/ https://www.planalto.gov.br/ccivil_03/_ato2023-2026/2023/lei/L14701.htm | R41: Norte

Sheet Falsas e exageradas
A1: ID | B1: Candidato | C1: Declaração | D1: Veredito | E1: Por quê
A2: F03 | B2: Flávio | C2: Regra do governo Bolsonaro garante pedágio zero para motociclistas em todas as novas concessões federais de rodovias. | D2: Exagerado | E2: A Portaria 104/2021 do Ministério da Infraestrutura fixou como diretriz a isenção de pedágio para motos nos editais de 11 rodovias federais então em licitação, como Dutra, Fernão Dias e BR-040. Não é uma regra que garanta a isenção em todas as novas concessões federais: cada contrato define a questão separadamente. A ideia de valer para todas foi uma promessa de Bolsonaro.
A3: F07 | B3: Flávio | C3: Foi Bolsonaro que estabeleceu o benefício mínimo de R$ 600 do Bolsa Família/Auxílio Brasil. | D3: Exagerado | E3: O governo Bolsonaro pagou o Auxílio Brasil de R$ 600 em 2022. O valor veio de um acréscimo temporário de R$ 200, aprovado pela chamada PEC das Bondades (ou PEC Kamikaze), que valia só até dezembro de 2022. Sem nova medida, o benefício voltaria a R$ 400 em janeiro de 2023. A manutenção dos R$ 600 em 2023 veio da PEC articulada pela equipe de transição de Lula, que ampliou o teto de gastos. O piso de R$ 600 por família, garantido por complementação, foi fixado pela Lei 14.601/2023, que recriou o Bolsa Família. Bolsonaro de fato pagou R$ 600, mas de forma temporária, e não estabeleceu o piso permanente.
A4: F08 | B4: Flávio | C4: Reduflação no governo Lula: dúzia de ovos virou caixa com 10, sabão em pó de 1 kg virou 800 g, barra de chocolate de 120 g virou 80 g, rolo de papel higiênico de 40 m virou 20 m. | D4: Exagerado | E4: A reduflação existe no Brasil e há casos documentados de caixas de ovos com 10 unidades, sabão em pó de 800 g e papel higiênico com menos metros. Mas é uma prática da indústria, anterior ao atual governo e que não resulta de política federal. Não encontrei os números exatos citados (chocolate de 120 g para 80 g, papel higiênico de 40 m para 20 m) como tendência geral.
A5: F11 | B5: Flávio | C5: Os juros reais do crédito do Plano Safra chegam perto de 20%, e o governo Lula contingencia recursos do seguro rural e do Plano Safra. | D5: Exagerado | E5: O bloqueio de recursos do seguro rural (PSR) em 2026 foi noticiado. Já os juros das linhas oficiais do Plano Safra 2026/27 estão bem abaixo de 20%: o Pronamp tem teto de 9% ao ano e o Pronaf é ainda mais barato. Descontada a inflação, o juro real das linhas equalizadas fica muito longe de 20%.
A6: F13 | B6: Flávio | C6: Lula já gastou mais de R$ 400 bilhões para tentar se reeleger (medidas não previstas no orçamento). | D6: Exagerado | E6: O Poder360 somou "ao menos R$ 403,2 bilhões" em programas sociais em 2026. A reportagem detalha só uma parte desse total: Bolsa Família (R$ 158,6 bilhões), Farmácia Popular (R$ 6 bilhões) e Gás do Povo (R$ 4,7 bilhões). Sobre o Gás do Povo, o texto diz que o valor está "reservado no Orçamento de 2026". Bolsa Família e Farmácia Popular são programas antigos que o governo retomou, não medidas improvisadas. Por isso, não se sustenta dizer que os R$ 400 bilhões foram gastos em medidas fora do orçamento, nem atribuir todo o valor ao esforço de reeleição. O número em si existe, mas foi apresentado de forma exagerada.
A7: F14 | B7: Flávio | C7: Nas enchentes de 2024 no RS, Lula não entregou nem 30% do que prometeu. | D7: Falso | E7: Segundo o Correio da Manhã (maio de 2026), cerca de R$ 90 bilhões federais já foram usados pelo RS e pelos municípios gaúchos na reconstrução, o equivalente a 94% do previsto no Auxílio Reconstrução. A ministra da Casa Civil, Miriam Belchior, disse que a meta é chegar a 100%. Já no fim de maio de 2024, segundo o InfoMoney, cerca de 57% estava pago em emendas parlamentares (R$ 743 milhões de R$ 1,3 bilhão) e em recursos da Defesa Civil (R$ 176 milhões de R$ 310 milhões). O problema real são os atrasos: o TCU (Acórdão 2470/2025) apontou demora no repasse de recursos e na entrega de obras municipais. Mesmo assim, nenhum dado indica entrega abaixo de 30% do prometido.
A8: F16 | B8: Flávio | C8: Por causa do atual governo, a meta de universalização do saneamento já foi empurrada para depois de 2050. | D8: Falso | E8: A meta legal de universalização continua em 2033. A proposta de adiá-la para 2040 é um projeto do deputado Amom Mandel (Cidadania-AM), e o ministro das Cidades, Jader Filho, disse ser 'absolutamente contrário' à prorrogação (Poder360, 06/06/2025). Existem projeções de que, no ritmo atual de investimento, a universalização só ocorreria depois de 2050. Mas são estimativas, algumas anteriores ao governo atual, e não uma mudança de meta feita pelo governo.
A9: F19 | B9: Flávio | C9: Lula prometeu entregar a transposição do São Francisco até 2009 e depois até 2014 e não entregou; foi Bolsonaro quem concluiu as obras e fez a água chegar ao Nordeste. | D9: Exagerado | E9: A obra começou em 2007 e 2008, no segundo mandato de Lula. A promessa original de conclusão era 2012, e os prazos foram descumpridos várias vezes nos governos do PT. Segundo o Poder360, os governos do PT investiram R$ 8,3 bilhões de um total de R$ 14,6 bilhões. Temer investiu R$ 2,8 bilhões e inaugurou a pré-operação do Eixo Leste em 2017, com água chegando à Paraíba e a Pernambuco. Bolsonaro investiu R$ 3,5 bilhões e concluiu e inaugurou trechos do Eixo Norte entre 2020 e 2022. Os eixos principais ficaram prontos em 2021, mas ramais seguiam inacabados.
A10: F25 | B10: Flávio | C10: Tarcísio, Ricardo Nunes e Derrite acabaram com a Cracolândia em São Paulo. | D10: Exagerado | E10: Em maio de 2025, a Rua dos Protestantes, onde ficava a principal concentração de usuários, amanheceu vazia (B News SP, 15/05/2025). Em novembro de 2025, Tarcísio escreveu que 'a cracolândia acabou'. Segundo o Jornal de Brasília, que reproduz a Folhapress (19/11/2025), outras aglomerações de usuários surgiram no centro depois disso. O próprio Ricardo Nunes admitiu: 'Não dá para dizer que a gente resolveu todo o problema'. A reportagem lembra ainda que as dispersões de 2012 e 2022 apenas criaram 'minicracolândias' em outros pontos. A queda foi real, mas dizer que eles 'acabaram' com a Cracolândia exagera. Nenhuma das fontes consultadas cita declaração de Derrite.
A11: F29 | B11: Flávio | C11: Após o 1º turno, com Flávio à frente nas pesquisas do 2º turno, a taxa de juros futuros caiu cerca de 2 pontos. | D11: Exagerado | E11: Os juros futuros caíram de fato depois do 1º turno, e o mercado associou o movimento ao 'trade eleitoral' a favor de Flávio. O DI para janeiro de 2029 foi de cerca de 13,7% antes da eleição para 12,22% em 9/10, uma queda de no máximo 1,5 ponto. Houve repique em 13/10 (12,22% para 12,50%) e a taxa estava em 12,58% em 20/10. A queda acumulada fica entre 1 e 1,5 ponto, não 2, e teve outros fatores: leilão do Tesouro, Treasuries e petróleo.
A12: F30 | B12: Flávio | C12: Lula criou ou aumentou mais de 30 impostos. | D12: Exagerado | E12: O Poder360 (09/10/2025) diz que o governo aumentou impostos 'ao menos 27 vezes desde 2023'. Essa conta só inclui tributos relevantes que elevaram a arrecadação de forma consistente. A Exame (17/06/2025) chega a 'ao menos 37', mas a lista mistura coisas diferentes: oito itens tratam da mesma MP 1.303, e entram medidas revogadas (a 'taxa das blusinhas' e o decreto do IOF), propostas não aprovadas (CSLL/JCP, dividendos) e até a defesa de Haddad da taxação de super-ricos no G20. Tirando esses itens, o total também fica abaixo de 30. Além disso, a frase fala em 'impostos', mas são medidas, e muitas apenas trazem de volta tributos que estavam zerados ou mudam regimes e benefícios. O número de impostos distintos criados ou aumentados é bem menor que 30. Houve muitos aumentos de tributos, mas 'mais de 30 impostos' exagera o que as fontes permitidas mostram.
... A29: L34 | B29: Lula | C29: Flávio, ganhando salário de parlamentar (~R$ 46 mil), comprou uma casa de cerca de R$ 10 milhões. | D29: Exagerado | E29: O registro em cartório do DF indica que a casa no Lago Sul foi comprada em 2021 por R$ 5,97 milhões, com financiamento de R$ 3,1 milhões no BRB. A desproporção em relação ao salário de senador existe: na época, o salário bruto era de cerca de R$ 33,7 mil, e a reportagem cita cerca de R$ 24 mil líquidos. Mas o valor de R$ 10 milhões quase dobra o preço de compra registrado.

Sheet Revisão independente
A1: ID | B1: Candidato | C1: Declaração | D1: Veredito pesquisa | E1: Veredito revisor (final) | F1: Concordou? | G1: O que o revisor confirmou/corrigiu
A2: F01 | B2: Flávio | C2: O governo Bolsonaro recebeu o país em 2019 com cerca de 14.000 obras inacabadas e entregou com pouco mais de 8.000. | D2: Verdadeiro, mas impreciso | E2: Verdadeiro, mas impreciso | F2: Sim | G2: REAVALIADO SEM FONTES ENVIESADAS. Veredito mantido. Saíram o 8.674 e o 14,4 mil em 38,4 mil, que só vinham da Gazeta do Povo. Entraram os números oficiais do TCU: 8.603 em 21.007 e cerca de 14 mil em 38 mil. O Jornal Opção não foi usado. Revisor: Abri todas as fontes citadas, e elas são permitidas e confirmam o que o agente afirma. O 8.603/21.007 e os 29% e 41% estão na notícia do TCU. O 14 mil em 38 mil está no relatório do TCU de 2019. A frase sobre a falta de política pública entre 2019 e 2022 está em O Povo. Um ajuste: a notícia do TCU dá como data dos dados a sessão de 18/10/2023, e a ligação com 2022 vem de O Povo. O texto foi ajustado para refletir isso. Nenhum dado depende de fonte excluída.
A3: F02 | B3: Flávio | C3: O TCU acaba de soltar (2026) relatório apontando mais de 11.500 obras paralisadas no atual governo. | D3: Verdadeiro, mas impreciso | E3: Verdadeiro, mas impreciso | F3: Sim | G3: REAVALIADO SEM FONTES ENVIESADAS. Nada mudou na substância. Revisor: Confirmei no TCU e no Viva os números 11.469 de 22.621 (50,7%), a data de 30/07/2025, a referência a abril de 2025 e as cerca de 1,2 mil paradas entre as 5.505 obras recentes. Acrescentei à explicação que 11.469 fica levemente abaixo de 'mais de 11.500'. Nenhum dado depende de fonte excluída.
A4: F03 | B4: Flávio | C4: Regra do governo Bolsonaro garante pedágio zero para motociclistas em todas as novas concessões federais de rodovias. | D4: Verdadeiro, mas impreciso | E4: Exagerado | F4: Não | G4: A base da pesquisa original está correta, mas o InfoMoney confirma que a portaria se limitava a 11 rodovias específicas e que cada contrato é negociado separadamente. Por isso a palavra 'garante' com 'todas as novas concessões' infla a medida, e mudei o veredito de 'Verdadeiro, mas impreciso' para 'Exagerado'. Descartei as fontes de blogs de motos.
A5: F04 | B5: Flávio | C5: O governo Bolsonaro instalou mais de 21.300 pontos de internet, em mais de 3.100 cidades, atendendo mais de 11 milhões de brasileiros (escolas, unidades de saúde, aldeias). | D5: Verdadeiro, mas impreciso | E5: Verdadeiro, mas impreciso | F5: Sim | G5: RECHECADO (2ª rodada). Concordo com o veredito e agora há confirmação do número exato, que o agente anterior não havia achado: o balanço oficial de dezembro de 2022 confirma 21,3 mil pontos, cerca de 3,2 mil cidades e mais de 11 milhões de pessoas. A ressalva sobre a origem no GESAC (2002) continua válida. Observação: o limite de buscas da sessão se esgotou depois da primeira consulta, então a revisão se apoiou em páginas abertas com WebFetch.
A6: F05 | B6: Flávio | C6: Lula implementou a carga tributária mais alta da história do país. | D6: Verdadeiro, mas impreciso | E6: Verdadeiro, mas impreciso | F6: Sim | G6: Confirmei os 32,4% e que a série do Tesouro começa em 2010. A ressalva sobre séries anteriores, com outra metodologia, segue válida. As fontes usadas são portais secundários que reproduzem o Tesouro. Não acessei a nota oficial do Tesouro porque o limite de buscas acabou.
A7: F06 | B7: Flávio | C7: A alíquota do novo IVA da reforma tributária é estimada em cerca de 28% e será o maior IVA do mundo; o governo já deveria ter enviado ao Congresso projeto definindo a alíquota. | D7: Verdadeiro, mas impreciso | E7: Verdadeiro, mas impreciso | F7: Sim | G7: Confirmei no InfoMoney os 28,55%, a comparação com a Hungria e o prazo de 2030/2031. A segunda parte da fala é falsa. Mantive 'Verdadeiro, mas impreciso' porque o núcleo da afirmação, a alíquota de cerca de 28% e o maior IVA do mundo, se sustenta. Seria defensável também chamar a fala inteira de 'Exagerada'.
A8: F07 | B8: Flávio | C8: Foi Bolsonaro que estabeleceu o benefício mínimo de R$ 600 do Bolsa Família/Auxílio Brasil. | D8: Exagerado | E8: Exagerado | F8: Sim | G8: REAVALIADO SEM FONTES ENVIESADAS. Veredito mantido. Saiu a Crusoé. A previsão do Orçamento de 2023 deu lugar ao dado confirmado de que o valor voltaria a R$ 400 em janeiro de 2023. Entrou a Lei 14.601/2023 como base do piso permanente. A referência ao número da EC 126 saiu. Revisor: O Correio Braziliense confirma a PEC das Bondades/Kamikaze e o acréscimo de R$ 200 válido até dezembro. O Jornal Contábil confirma a volta a R$ 400 sem nova medida e a PEC da equipe de Lula que ampliou o teto. A Câmara confirma o piso de R$ 600 por complementação na Lei 14.601/2023. A página do Planalto não abriu (timeout) e foi retirada das fontes, o que não muda o resultado porque a Câmara já confirma a lei. Tirei também o 'a partir de agosto', que nenhuma das fontes abertas confirma de forma explícita. Nenhum dado depende de fonte excluída.
A9: F08 | B9: Flávio | C9: Reduflação no governo Lula: dúzia de ovos virou caixa com 10, sabão em pó de 1 kg virou 800 g, barra de chocolate de 120 g virou 80 g, rolo de papel higiênico de 40 m virou 20 m. | D9: Exagerado | E9: Exagerado | F9: Sim | G9: Concordo. O limite de buscas da sessão acabou, então não pude fazer busca nova. Lembro, de conhecimento prévio, que a regra federal que obriga avisar o consumidor sobre redução de quantidade (Portaria MJSP 392/2021) é de 2021, antes do atual governo. Isso reforça que a prática não começou com Lula. O link do ABCdoABC é de portal regional que repete um alerta do Procon; tem valor secundário.
A10: F09 | B10: Flávio | C10: O Brasil tem uma das maiores taxas de juros do mundo. | D10: Verdadeiro | E10: Verdadeiro | F10: Sim | G10: Concordo. Não consegui fazer busca nova porque o limite de buscas acabou. A afirmação é genérica ("uma das maiores") e condiz com o histórico sabido da Selic e com as reportagens citadas, que são de portais de notícias.
A11: F10 | B11: Flávio | C11: Lula chamou o agro de fascista e disse que as pessoas (do agro) têm que se ajoelhar aos seus pés. | D11: Verdadeiro, mas impreciso | E11: Verdadeiro, mas impreciso | F11: Sim | G11: Concordo com o veredito. A fala de 2022 sobre parte do agro ser fascista está bem documentada. Não consegui abrir a fonte da fala do "ajoelhar" (o Canal Rural bloqueou o acesso, erro 403) e o limite de buscas acabou. Por isso essa parte depende só da fonte original, o que reduz a confiança.
A12: F11 | B12: Flávio | C12: Os juros reais do crédito do Plano Safra chegam perto de 20%, e o governo Lula contingencia recursos do seguro rural e do Plano Safra. | D12: Exagerado | E12: Exagerado | F12: Sim | G12: Confirmei no Times Brasil e no AgFeed o teto de 9% do Pronamp e que nenhum dos dois fala em 20%. As duas reportagens não informam a taxa de 12,5% do custeio empresarial que a pesquisa original atribuiu a elas. Não consegui abrir a matéria do Canal Rural sobre o bloqueio de R$ 461,7 milhões (erro 403). O AgFeed mostra ainda que o volume de custeio caiu cerca de 11% em termos reais, o que dá alguma base à crítica de aperto no crédito. A parte dos juros de 20% continua sem sustentação para o crédito oficial.
... A92: L35 | B92: Lula | C92: O governo Bolsonaro gastou cerca de 30% a mais no cartão corporativo que o governo Lula. | D92: Verdadeiro, mas impreciso | E92: Verdadeiro, mas impreciso | F92: Sim | G92: REAVALIADO SEM FONTES ENVIESADAS. O veredito não mudou. A Gazeta do Povo (excluída) foi retirada, e nenhum dado dela foi usado. Os percentuais anuais foram recalculados só com os números do Terra, e estão corretos. Revisor: Confirmei pelo WebFetch os números citados do Terra. Há uma ressalva: o Terra atribui os números da Secretaria ao Aos Fatos e os da Presidência ao Estadão Verifica, que são checagens, e não informa a fonte do total do governo federal. Ainda assim, a fonte usada é o Terra, um portal jornalístico, com dados que vêm do Portal da Transparência. Nenhuma fonte excluída foi usada. A confiança Média se justifica por essa origem indireta dos números e pela divergência de metodologias.

Sheet Fontes
A1: ID | B1: Candidato | C1: Origem | D1: Fonte / URL
A2: F01 | B2: Flávio | C2: Revisor | D2: https://portal.tcu.gov.br/imprensa/noticias/brasil-tem-86-mil-obras-paralisadas-financiadas-com-recursos-federais
A3: F01 | B3: Flávio | C3: Revisor | D3: https://sites.tcu.gov.br/relatorio-de-politicas/2019/area_12.htm
A4: F01 | B4: Flávio | C4: Revisor | D4: https://www.opovo.com.br/noticias/economia/2023/10/18/tcu-diz-que-nao-existiu-entre-2019-e-2022-politicas-para-obras-paralisadas-e-cobra-medidas.html
A5: F02 | B5: Flávio | C5: Revisor | D5: https://portal.tcu.gov.br/imprensa/noticias/metade-das-obras-financiadas-com-recursos-federais-estao-paradas
A6: F02 | B6: Flávio | C6: Revisor | D6: https://viva.com.br/noticias/brasil-tem-mais-de-11-mil-obras-paradas-para-tcu-volume-e-preocupante.html
A7: F03 | B7: Flávio | C7: Revisor | D7: https://www.infomoney.com.br/?p=1881372
A8: F03 | B8: Flávio | C8: Revisor | D8: https://oespecialista.safra.com.br/tcu-aprova-concessao-da-dutra-e-isencao-de-pedagio-para-motos/
A9: F03 | B9: Flávio | C9: Pesquisa inicial | D9: https://www.motoo.com.br/novas-concessoes-de-rodovias-federais-terao-isencao-de-pedagio-para-motos/
A10: F03 | B10: Flávio | C10: Pesquisa inicial | D10: https://www.agazeta.com.br/es/economia/motos-ficarao-livres-de-pagar-pedagio-na-br-262-apos-concessao-0721
A11: F04 | B11: Flávio | C11: Revisor | D11: https://www.nic.br/noticia/na-midia/mais-de-21-3-mil-pontos-de-internet-do-wi-fi-brasil-sao-instalados/
A12: F04 | B12: Flávio | C12: Revisor | D12: https://agenciabrasil.ebc.com.br/geral/noticia/2021-04/programa-leva-internet-areas-remotas-do-pais
... A517: PL13 | B517: Lula | C517: Revisor | D517: https://www.planalto.gov.br/ccivil_03/_ato2023-2026/2023/lei/L14701.htm

Sheet Fontes excluídas
A1: Veículos excluídos nesta versão (fontes com viés político declarado ou baixa confiabilidade)
A2: Critério simétrico: saíram veículos militantes ou com alinhamento partidário declarado, dos dois lados do espectro, além de fontes abertas não jornalísticas. Também saíram Gazeta do Povo e Sul21, que têm linha editorial declarada (conservadora e progressista). Jornais tradicionais sem alinhamento declarado foram mantidos.
A4: Veículo | B4: Domínio | C4: Motivo da exclusão | D4: Referências removidas
A5: CartaCapital | B5: cartacapital.com.br | C5: linha editorial de esquerda declarada; apoio editorial a candidatos do PT | D5: 6
A6: Brasil de Fato | B6: brasildefato.com.br | C6: veículo ligado a movimentos sociais de esquerda (MST) | D6: 1
A7: Portal Vermelho | B7: vermelho.org.br | C7: órgão de comunicação do PCdoB | D7: 1
A8: Fundação Perseu Abramo | B8: fpabramo.org.br | C8: fundação partidária do PT | D8: 1
A9: O Cafezinho | B9: ocafezinho.com | C9: blog militante de esquerda | D9: 1
A10: ICL Notícias | B10: iclnoticias.com.br | C10: veículo de opinião alinhado à esquerda | D10: 2
A11: TVT | B11: tvtnews.com.br | C11: emissora ligada a sindicatos (CUT/Metalúrgicos do ABC) | D11: 1
A12: Revista Oeste | B12: revistaoeste.com | C12: linha editorial de direita declarada; alinhada ao bolsonarismo | D12: 3
A13: Crusoé | B13: crusoe.com.br | C13: revista de opinião de oposição ao PT | D13: 2
A14: O Antagonista | B14: oantagonista.com.br | C14: site de opinião de oposição ao PT | D14: 1
A15: Jovem Pan | B15: jovempan.com.br | C15: histórico de alinhamento ao bolsonarismo; alvo de ação do MPF/TSE por desinformação | D15: 6
A16: Diário do Poder | B16: diariodopoder.com.br | C16: site de linha editorial de direita/oposição | D16: 1
... A20: Sul21 | B20: sul21.com.br | C20: linha editorial progressista declarada | D20: 4
A22: Referências removidas, item a item
A23: ID | B23: Etapa | C23: Veículo | D23: Fonte removida
A24: F01 | B24: Etapa inicial | C24: Gazeta do Povo | D24: https://www.gazetadopovo.com.br/republica/numero-de-obras-paradas-cresce-38-no-governo-lula-e-8-mil-nao-tem-previsao-de-conclusao/
A25: F01 | B25: Final (revisor) | C25: Gazeta do Povo | D25: https://www.gazetadopovo.com.br/republica/numero-de-obras-paradas-cresce-38-no-governo-lula-e-8-mil-nao-tem-previsao-de-conclusao/
A26: F02 | B26: Final (revisor) | C26: Gazeta do Povo | D26: https://www.gazetadopovo.com.br/republica/numero-de-obras-paradas-cresce-38-no-governo-lula-e-8-mil-nao-tem-previsao-de-conclusao/
A27: F07 | B27: Etapa inicial | C27: Crusoé | D27: https://crusoe.com.br/diario/equipe-de-lula-defende-pec-de-transicao-para-bancar-auxilio-brasil-de-r-600
A28: F07 | B28: Final (revisor) | C28: Crusoé | D28: https://crusoe.com.br/diario/equipe-de-lula-defende-pec-de-transicao-para-bancar-auxilio-brasil-de-r-600
A29: F13 | B29: Etapa inicial | C29: Diário do Poder | D29: https://diariodopoder.com.br/brasil-e-regioes/e02-brasil/governo-lula-amplia-beneficios-sociais-em-ano-eleitoral-com-impacto-de-r-187-bilhoes
A30: F14 | B30: Etapa inicial | C30: Gazeta do Povo | D30: https://www.gazetadopovo.com.br/republica/governo-federal-recursos-anunciados-reconstrucao-rs/
A31: F14 | B31: Final (revisor) | C31: Gazeta do Povo | D31: https://www.gazetadopovo.com.br/republica/governo-federal-recursos-anunciados-reconstrucao-rs/
A32: F23 | B32: Etapa inicial | C32: Portal Vermelho | D32: https://vermelho.org.br/?p=749499
A33: F23 | B33: Etapa inicial | C33: CartaCapital | D33: https://www.cartacapital.com.br/sociedade/para-cada-feminicidio-consumado-em-2025-houve-quase-tres-tentativas-mostra-anuario/
A34: F23 | B34: Final (revisor) | C34: CartaCapital | D34: https://www.cartacapital.com.br/sociedade/para-cada-feminicidio-consumado-em-2025-houve-quase-tres-tentativas-mostra-anuario/
... A75: PL11 | B75: Final (revisor) | C75: Gazeta do Povo | D75: https://www.gazetadopovo.com.br/economia/bets-pedem-stf-derrubar-suspensao-lula/

Sheet Metodologia
A1: Vídeo analisado | B1: https://youtu.be/TgK9ZAiNi_4 — "Flávio Bolsonaro ESTÁ PRONTO!! Ele foi BRILHANTE no DEBATE da GLOBO contra o LULA!!! | Completo" (canal Marco Feliciano, 1h54min58s)
A2: Evento | B2: Último debate do 2º turno da eleição presidencial de 2026, TV Globo, 23/10/2026. Mediação: César Tralli.
A3: Observação sobre a fonte | B3: O título do vídeo é opinativo e o canal é de um político aliado de um dos candidatos. A checagem usa só as falas do debate, sem levar o título em conta.
A4: Transcrição | B4: Legenda automática do YouTube (pt). Nomes e números podem ter erros de transcrição; nesses casos, a declaração foi interpretada pelo contexto.
A5: Seleção das declarações | B5: Foram incluídas afirmações factuais verificáveis (números, fatos, atos e falas atribuídas). Ficaram de fora promessas, opiniões, ataques pessoais e frases genéricas.
A6: Processo | B6: 1) Um agente pesquisador fez uma busca independente na internet para cada declaração (lotes de 7). 2) Um agente revisor independente refez a busca do zero, conferiu as fontes e o raciocínio do primeiro e deu o veredito final. 3) O placar conta o veredito final do revisor.
A7: Data da checagem | B7: 24/10/2026
A8: Verdadeiro | B8: A afirmação confere com os dados.
A9: Verdadeiro, mas impreciso | B9: A essência está correta, mas há números ou detalhes aproximados ou incompletos.
A10: Exagerado | B10: Tem base real, mas está inflado, distorcido ou fora de contexto.
A11: Falso | B11: Os dados contradizem a afirmação.
A12: Sem evidência | B12: Não foi possível comprovar nem refutar com fontes confiáveis (inclui fatos muito recentes ainda sem registro).
... A18: Versão com fontes filtradas | B18: Esta cópia remove as referências de veículos com viés político declarado ou baixa confiabilidade (lista na aba "Fontes excluídas"), além de frases das explicações que dependiam deles. Os dados que vinham só desses veículos foram desconsiderados: os 32 itens afetados foram reavaliados por um agente e conferidos por um revisor independente, usando só as fontes restantes e buscas novas que bloqueavam os sites excluídos. O L16 foi refeito à parte. Os placares foram recalculados. Nenhum item ficou sem fonte.

Sheet Transcrição
A1: Minuto | B1: Texto (legenda automática)
A2: 00:00 | B2: Bem-vindos aos Estúdios Globo, pro último debate com os candidatos [música] que disputam a presidência da República neste segundo turno. Uma oportunidade para você, eleitor e eleitora, avaliar as propostas dos candidatos [música] antes da votação decisiva de domingo. Nós recebemos aqui Flávio Bolsonaro do PL e Luís Inácio Lula da Silva do PT. Muito obrigado pela presença dos senhores. A plateia pode aproveitar esse momento para dar boas-vindas aos dois candidatos com uma salva de palmas. [aplausos] [música] » [música] » Agradeço muito aqui a presença de todos e a partir de agora eu peço à plateia que fique em silêncio para não prejudicar os candidatos e principalmente os eleitores. A nossa transmissão é ao vivo aqui na Globo, na
A3: 00:01 | B3: Globo News, no G1 e no Globo Play. Vamos juntos agora conferir as regras do nosso debate. » O debate tem quatro blocos. Os três primeiros são de temas determinados, o quarto de tema livre e com as considerações finais. As regras priorizam o interesse do eleitor e esse objetivo fica evidente no centro do nosso cenário. O mapa gigante do Brasil é um convite para que os candidatos apresentem propostas ao país. No primeiro bloco estarão em debate planos para cinco regiões do Brasil: Sul, Sudeste, Centro-Oeste, Norte e Nordeste. O sexto tema neste primeiro bloco é estratégico. Que projetos os candidatos têm no setor de infraestrutura para aumentar as exportações brasileiras. O mapa vai iluminar rodovias, ferrovias, hidrovias e portos. O segundo bloco e o
A4: 00:02 | B4: terceiro tem 10 questões fundamentais para o futuro do Brasil. E os candidatos vão escolher seis desses temas, três no segundo bloco e três no terceiro bloco. Os assuntos são os seguintes: endividamento dos brasileiros, ensino integral, dívida pública, inteligência artificial, meio ambiente, políticas sociais, reformas, relações com Estados Unidos e China, retomada de territórios, Sistema Único de Saúde. Sobre a dinâmica do debate. As perguntas são de candidato para candidato e vai haver um banco de tempo em cada rodada. Nos três primeiros blocos, o candidato tem um total de 3 minutos para a pergunta e a réplica, e o adversário terá a mesma quantidade de tempo, 3 minutos para a resposta e a tréplica. Nesses momentos, quem expõe sua proposta pode andar livremente pelo
A5: 00:03 | B5: cenário e nessa hora o outro candidato deve aguardar no púlpito até o fim da manifestação do adversário. No quarto e último bloco de tema livre, cada candidato terá 8 minutos para usar o banco de tempo como quiser e quantas vezes quiser até o cronômetro zerar. Nessa hora, os candidatos podem andar livremente pelo cenário, mas sem invadir o espaço do outro. Este é um debate para as ideias circularem livremente em um ambiente criado e construído para isso. Os candidatos apresentam suas visões pro futuro do país e dezenas de milhões de eleitores comparam. É a democracia ao vivo na Globo. » Se um candidato fizer ofensas pessoais a outro, o candidato ofendido poderá pedir direito de resposta. Para isso, deverá levantar a mão em silêncio. A nossa produção vai avaliar se o direito de resposta será ou não concedido. Em
A6: 00:04 | B6: respeito ao eleitor, nós esperamos que os candidatos façam um debate de alto nível com propostas para governar o país. O fato ou fake, serviço de checagem do grupo Globo, vai verificar as declarações dos dois candidatos ao longo do debate. Neste momento, mais de 30 jornalistas já estão trabalhando juntos com essa missão em busca do máximo rigor e agilidade. Você pode acompanhar ao vivo as nossas checagens feitas durante e depois do debate. Para isso, basta apontar o seu celular para esse QRcode aqui que tá aparecendo na tela. Ele vai te levar pro G1 e no G1 você encontra as checagens das entrevistas concedidas por Flávio Bolsonaro e Lula à jornalista Renata Lopret aqui na Globo na semana passada. E ainda as verificações feitas durante o
A7: 00:05 | B7: debate da Band no último domingo. Um outro caminho para você acompanhar as nossas checagens é entrar nos sites jornais O Globo, Valor Econômico Extra e no site da Rádio CBN. Também estão fazendo a checagem do debate de hoje outras importantes agências de verificação de fatos, como a Lupa em parceria com o jornal Folha de São Paulo, a agência aos fatos, o Wall confere, o Estadão verifica e ainda o projeto comprova. Vamos então começar o nosso debate. Lembrando que neste primeiro bloco o tema é determinado. A pergunta deve abordar questões, propostas e desafios relacionados à região ou ao tema sorteados. Quem está com a palavra pode andar pelo cenário sem ser interrompido e o adversário aguarda no púlpito a vez de falar. Vou então fazer o sorteio aqui
A8: 00:06 | B8: para ver quem vai começar o nosso debate, quem abre o debate essa noite e quem abre o debate é o candidato Flávio Bolsonaro do PL. Candidatos, se o senhor quiser vir já pro mapa, eu vou sortear agora a região ou o tema. E o tema é infraestrutura e exportação. O senhor vai ver aí no mapa as principais rotas usadas para escoar a produção brasileira. As rodovias estão em laranja, as ferrovias estão em verde, as hidrovias em azul e na costa brasileira os nossos principais portos. Quais são os investimentos fundamentais em infraestrutura para aumentar as exportações brasileiras e reduzir o custo Brasil? Então, peço ao senhor agora que, por favor, elabore a sua pergunta sobre esse tema.
A9: 00:07 | B9: » Boa noite a senhora senhor que tá em casa me acompanhando, a sua família. Boa noite, Tral. Obrigado pelo grupo Globo a oportunidade de estar aqui debatendo. Boa noite, meu concorrente candidato. Bom, nós pegamos o Brasil lá em 2019 com cerca de 14.000 obras inacabadas e apesar de todos os problemas, a gente entregou o Brasil com um pouco mais de 8.000 obras inacabadas. Agora, neste ano, o TCU, o Tribunal de Contas da União, acaba de soltar um relatório que existem mais de 11.500 obras paralisadas do atual governo. Ou seja, o Brasil voltou a ser um grande cemitério de obras. Candidato, como é que você vai conseguir entregar toda essa infraestrutura que tá aqui nesse mapa se você em 4 anos não entregou as obras necessárias? » Primeiro, [limpando a garganta] boa noite, Tral. Boa noite, candidato. Boa noite, povo brasileiro. E eu quero agradecer a Deus
A10: 00:08 | B10: a oportunidade de poder estar participando de um debate num momento tão especial como do Brasil. Eu penso que se o candidato conhecesse um pouco o Brasil, ele saberia que em nenhum momento da história do país se investiu tanto em obra de infraestrutura como nós investimos nesses últimos anos. Só para ter ideia, com a participação inclusive de todos os governadores, de todos os partidos políticos, nós anunciamos um programa de aceleração do crescimento de 1 trilhão700 bilhões, do quase 800 já foram executados nesse país, criando ferrovia, rodovia, hidrovia, estrada e portos e aeroportos para que a gente possa fazer com que o Brasil se transforme num grande país produtor de alimento, mas num grande país todo alimento. E o meu adversário sabe que qualquer coisa que
A11: 00:09 | B11: ele pensar de infraestrutura, nós fizemos três ou quatro vezes mais do que o governo deles fizeram. E mais importante saber ainda é que nós herdamos 6.000 1000 obras paradas e obviamente que você não consegue fazer obras de infraestrutura no mesmo ano que você começa. As obras que estão sendo feitas, eu vou continuá-las porque eu vou ganhar as eleições. » A sua réplica, candidato Flávio. » Bom, eu quero investir em infraestrutura. Eu vou rasgar esse Brasil de ferrovias. Eu vou concluir a transnodestina, que é para escoar a produção do nosso país para os portos de SUAP, no Pernambuco, e também para o porto de PEN. Eu quero dizer para vocês que eu vou fazer o eixo sul da ferroia que tá faltando, ligando o Centro-Oeste até o oeste do Paraná, oeste de Santa Catarina, que são regiões grandes produtoras de suinos, de proteínas. E é para lá que tem que chegar esses grãos de uma forma mais barata, mais rápida e com menos desperdício. Eu vou fazer de
A12: 00:10 | B12: novo, eu vou investir muito aqui na concessão de rodovias, como fez o presidente Bolsonaro. Eu vou manter uma regra que ele colocou lá. Todas as concessões de rodovias que forem feitas no Brasil vão garantir que é pedágio zero para motociclistas. E muito mais do que isso, eu vou investir e vou tratar a internet como infraestrutura, como fez, como começou a fazer o presidente Bolsonaro. Nós instalamos mais de 21.300 pontos de internet em vários locais do Brasil, atingindo mais de 3100 cidades e abrangendo mais de 11 mil, atendendo a mais de 11 milhões de brasileiros. Aonde, gente? em escolas, em unidades de saúde, nós vamos tratar a internet como estrutura para levar para as aldeias indígenas a conexão via internet. Esse é o Brasil que eu quero, um Brasil conectado. A internet é importante, por exemplo, paraa agricultura de precisão, o nosso agro pode crescer ainda mais se tiver estrutura, infraestrutura de internet
... A116: 01:54 | B116: medo na rua? Você tá andando com mais medo. Você tá devendo mais ou menos por causa do atual governo? Você tá devendo mais. Então eu quero te pedir humildemente, vote em Flávio Bolsonaro 22 pelo futuro, pelo futuro do da nossa nação, pelo futuro do nosso Brasil, pelo futuro da sua família, pelo seu futuro, pelo futuro dessa criança que tá aí a essa hora já no quarto do lado dormindo. O Brasil tem futuro. Eu quero agradecer de coração a cada um de vocês. Boto 22 na urna, olha no meu olho naquele momento só nós dois. Não aceite ameaças. Eu quero encerrar aqui pedindo que você em casa reze um Pai Nosso para que a nação brasileira possa se sentir tocada por Deus e tomar decisão correta no candidato Flávio. Nós encerramos assim o último debate neste segundo turno com os Muito obrigado aos candidatos, à plateia de convidados também e muito obrigado especialmente a você, eleitor e eleitora. Boa noite,
